[{"url":"https://twitter.com/theapeterminal/status/1734253718772629762","author_name":"Ape Terminal","author_url":"https://twitter.com/theapeterminal","html":"<blockquote class=\"twitter-tweet\"><p lang=\"en\" dir=\"ltr\">Ape Terminal IDO #2<br>AIT Protocol - <a href=\"https://twitter.com/AITProtocol?ref_src=twsrc%5Etfw\">@AITProtocol</a> <br><br>🟠 AIT is the 1st incubation of <a href=\"https://twitter.com/search?q=%24PAAL&amp;src=ctag&amp;ref_src=twsrc%5Etfw\">$PAAL</a> ecosystem, a token that delivered 100x growth this year, and has a 110M+ mcap.<br><br>🟠 Meanwhile, AIT mcap starts at just 500k.<br><br>🟠 AIT pioneers the first Train-2-Earn model. Train ML algorithms… <a href=\"https://t.co/AZZlDnlISY\">pic.twitter.com/AZZlDnlISY</a></p>&mdash; Ape Terminal (@theapeterminal) <a href=\"https://twitter.com/theapeterminal/status/1734253718772629762?ref_src=twsrc%5Etfw\">December 11, 2023</a></blockquote>\n<script async src=\"https://platform.twitter.com/widgets.js\" charset=\"utf-8\"></script>\n\n","width":550,"height":null,"type":"rich","cache_age":"3153600000","provider_name":"Twitter","provider_url":"https://twitter.com","version":"1.0"},{"url":"https://twitter.com/LedgerQL/status/1648399734653042688","author_name":"LedgerQL","author_url":"https://twitter.com/LedgerQL","html":"<blockquote class=\"twitter-tweet\"><p lang=\"en\" dir=\"ltr\">This trader made a 692k% unrealized profit on buy #1 of <a href=\"https://twitter.com/pepecoineth?ref_src=twsrc%5Etfw\">@pepecoineth</a>, and 303k% on buy #2, transforming $262.68 of <a href=\"https://twitter.com/search?q=%24PEPE&amp;src=ctag&amp;ref_src=twsrc%5Etfw\">$PEPE</a> into $1M<a href=\"https://t.co/tuVvE49yEH\">https://t.co/tuVvE49yEH</a> <a href=\"https://t.co/fNPS51HKBt\">pic.twitter.com/fNPS51HKBt</a></p>&mdash; Yannick M (King Nick) (@JustDoingItBig) <a href=\"https://twitter.com/JustDoingItBig/status/1648399309816176640?ref_src=twsrc%5Etfw\">April 18, 2023</a></blockquote>\n<script async src=\"https://platform.twitter.com/widgets.js\" charset=\"utf-8\"></script>\n\n","width":550,"height":null,"type":"rich","cache_age":"3153600000","provider_name":"Twitter","provider_url":"https://twitter.com","version":"1.0"},{"url":"https://twitter.com/427figs/status/1557534489156657155","author_name":"4FigsTo7Figs","author_url":"https://twitter.com/427figs","html":"<blockquote class=\"twitter-tweet\"><p lang=\"en\" dir=\"ltr\">15 New Projects With No Token, List #2<br><br>Some of these are already live on the Optimism <a href=\"https://twitter.com/search?q=%24OP&amp;src=ctag&amp;ref_src=twsrc%5Etfw\">$OP</a>,  Arbitrum <a href=\"https://twitter.com/search?q=%24ARB&amp;src=ctag&amp;ref_src=twsrc%5Etfw\">$ARB</a>, and Zksync <a href=\"https://twitter.com/search?q=%24ZKS&amp;src=ctag&amp;ref_src=twsrc%5Etfw\">$ZKS</a> networks.<br><br>So let&#39;s directly jump into the project list... <a href=\"https://t.co/qrHmL4byUA\">pic.twitter.com/qrHmL4byUA</a></p>&mdash; Airdrop Official 🦇🔊 (@its_airdrop) <a href=\"https://twitter.com/its_airdrop/status/1557339814273630208?ref_src=twsrc%5Etfw\">August 10, 2022</a></blockquote>\n<script async src=\"https://platform.twitter.com/widgets.js\" charset=\"utf-8\"></script>\n\n","width":550,"height":null,"type":"rich","cache_age":"3153600000","provider_name":"Twitter","provider_url":"https://twitter.com","version":"1.0"}]