[{"__typename":"Tweet","lang":"en","favorite_count":18,"created_at":"2023-12-29T12:27:16.000Z","display_text_range":[0,135],"entities":{"hashtags":[],"urls":[],"user_mentions":[{"id_str":"1465153318762598401","indices":[23,34],"name":"RCSV.io","screen_name":"BitmapTech"},{"id_str":"1669175947667578881","indices":[35,42],"name":"Recursiverse","screen_name":"rcsvio"}],"symbols":[]},"id_str":"1740711077661597953","text":"JUST GOT IN TOUCH WITH @BitmapTech @rcsvio. THEY'RE STILL FIXING THE DEPLOYMENT FUNCTION. WE'LL BEGIN OUR DEPLOYMENT ONCE IT'S FIXED.🙏","user":{"id_str":"1385494286108557313","name":"CHIPCHIPGAME 🏆CHIPCHIPBOX丨10K🎁","profile_image_url_https":"https://pbs.twimg.com/profile_images/1733496753062887424/JNK5LKQK_normal.jpg","screen_name":"chipchipgame","verified":false,"is_blue_verified":false,"profile_image_shape":"Circle"},"edit_control":{"edit_tweet_ids":["1740711077661597953"],"editable_until_msecs":"1703856436000","is_edit_eligible":true,"edits_remaining":"5"},"conversation_count":52,"news_action_type":"conversation","isEdited":false,"isStaleEdit":false}]