[{"__typename":"Tweet","lang":"en","favorite_count":45,"possibly_sensitive":false,"created_at":"2023-12-19T14:07:44.000Z","display_text_range":[0,259],"entities":{"hashtags":[],"urls":[{"display_url":"birdeye.so/token/GunZTF1t…","expanded_url":"https://birdeye.so/token/GunZTF1tjip5SxjE2jdeNGDi1HXHrcx9sLEJZHwv3fEp?chain=solana","indices":[233,256],"url":"https://t.co/sYgmnqVwoB"}],"user_mentions":[],"symbols":[{"indices":[0,7],"text":"SOLGUN"}],"media":[{"display_url":"pic.twitter.com/NbRuDKcSdD","expanded_url":"https://twitter.com/RaAr3s/status/1737112480974012661/photo/1","indices":[260,283],"url":"https://t.co/NbRuDKcSdD"}]},"id_str":"1737112480974012661","text":"$SOLGUN just launched. Initial dump was caused by private sale getting tokens, paper hands mostly out, now we are left with the project itself and people that believe in it. Let`s see how this goes, I know some good KOLs behind it.\n\nhttps://t.co/sYgmnqVwoB ✅… https://t.co/NbRuDKcSdD","user":{"id_str":"1240381065795166209","name":"RaArΞs ⚓️","profile_image_url_https":"https://pbs.twimg.com/profile_images/1645735999723524098/CAB-mBP3_normal.png","screen_name":"RaAr3s","verified":false,"is_blue_verified":true,"profile_image_shape":"Hexagon"},"edit_control":{"initial_tweet_id":"1737112352489910565","edit_tweet_ids":["1737112352489910565","1737112480974012661"],"editable_until_msecs":"1702998433000","is_edit_eligible":true,"edits_remaining":"4"},"mediaDetails":[{"display_url":"pic.twitter.com/NbRuDKcSdD","expanded_url":"https://twitter.com/RaAr3s/status/1737112480974012661/photo/1","ext_media_availability":{"status":"Available"},"indices":[260,283],"media_url_https":"https://pbs.twimg.com/media/GBt2TAPbgAAid1V.jpg","original_info":{"height":816,"width":1714,"focus_rects":[{"x":0,"y":0,"w":1457,"h":816},{"x":0,"y":0,"w":816,"h":816},{"x":0,"y":0,"w":716,"h":816},{"x":10,"y":0,"w":408,"h":816},{"x":0,"y":0,"w":1714,"h":816}]},"sizes":{"large":{"h":816,"resize":"fit","w":1714},"medium":{"h":571,"resize":"fit","w":1200},"small":{"h":324,"resize":"fit","w":680},"thumb":{"h":150,"resize":"crop","w":150}},"type":"photo","url":"https://t.co/NbRuDKcSdD"}],"photos":[{"backgroundColor":{"red":204,"green":214,"blue":221},"cropCandidates":[{"x":0,"y":0,"w":1457,"h":816},{"x":0,"y":0,"w":816,"h":816},{"x":0,"y":0,"w":716,"h":816},{"x":10,"y":0,"w":408,"h":816},{"x":0,"y":0,"w":1714,"h":816}],"expandedUrl":"https://twitter.com/RaAr3s/status/1737112480974012661/photo/1","url":"https://pbs.twimg.com/media/GBt2TAPbgAAid1V.jpg","width":1714,"height":816}],"conversation_count":6,"news_action_type":"conversation","quoted_tweet":{"lang":"en","reply_count":30,"retweet_count":31,"favorite_count":107,"possibly_sensitive":false,"created_at":"2023-12-19T12:59:54.000Z","display_text_range":[0,265],"entities":{"hashtags":[],"urls":[{"display_url":"dexscreener.com/solana/8SPngxi…","expanded_url":"https://dexscreener.com/solana/8SPngxiLd6QZMjtaJsEfN5vyPCFWDsyi6apUdg47cBGf","indices":[120,143],"url":"https://t.co/IrQvwrtoNK"},{"display_url":"raydium.io/swap/?inputCur…","expanded_url":"https://raydium.io/swap/?inputCurrency=sol&outputCurrency=GunZTF1tjip5SxjE2jdeNGDi1HXHrcx9sLEJZHwv3fEp&outputSymbol=GunZTF&fixed=in","indices":[150,173],"url":"https://t.co/3O2IinZuej"}],"user_mentions":[],"symbols":[{"indices":[21,28],"text":"SOLGUN"}],"media":[{"display_url":"pic.twitter.com/HMfmFJ1S29","expanded_url":"https://twitter.com/SolanaGun/status/1737095410454569067/photo/1","indices":[265,288],"url":"https://t.co/HMfmFJ1S29"}]},"id_str":"1737095410454569067","text":"SOLdiers, Its Time!\n\n$SOLGUN is now trading on Raydium🚀\n\nCA- GunZTF1tjip5SxjE2jdeNGDi1HXHrcx9sLEJZHwv3fEp\n\nDexscreener- https://t.co/IrQvwrtoNK\n\nBuy- https://t.co/3O2IinZuej\n\nNOTE: In Raydium, sometimes occurs an issue of adding new CA. please be patient for that. https://t.co/HMfmFJ1S29","user":{"id_str":"1724081180474019840","name":"SolanaGun","profile_image_url_https":"https://pbs.twimg.com/profile_images/1726538327493599232/SOgGfUJg_normal.jpg","screen_name":"SolanaGun","verified":false,"is_blue_verified":false,"profile_image_shape":"Circle"},"edit_control":{"edit_tweet_ids":["1737095410454569067"],"editable_until_msecs":"1702994394000","is_edit_eligible":true,"edits_remaining":"5"},"mediaDetails":[{"display_url":"pic.twitter.com/HMfmFJ1S29","expanded_url":"https://twitter.com/SolanaGun/status/1737095410454569067/photo/1","ext_media_availability":{"status":"Available"},"indices":[265,288],"media_url_https":"https://pbs.twimg.com/media/GBtnDK4bEAAGL3y.jpg","original_info":{"height":1024,"width":1024,"focus_rects":[{"x":0,"y":98,"w":1024,"h":573},{"x":0,"y":0,"w":1024,"h":1024},{"x":37,"y":0,"w":898,"h":1024},{"x":230,"y":0,"w":512,"h":1024},{"x":0,"y":0,"w":1024,"h":1024}]},"sizes":{"large":{"h":1024,"resize":"fit","w":1024},"medium":{"h":1024,"resize":"fit","w":1024},"small":{"h":680,"resize":"fit","w":680},"thumb":{"h":150,"resize":"crop","w":150}},"type":"photo","url":"https://t.co/HMfmFJ1S29"}],"photos":[{"backgroundColor":{"red":204,"green":214,"blue":221},"cropCandidates":[{"x":0,"y":98,"w":1024,"h":573},{"x":0,"y":0,"w":1024,"h":1024},{"x":37,"y":0,"w":898,"h":1024},{"x":230,"y":0,"w":512,"h":1024},{"x":0,"y":0,"w":1024,"h":1024}],"expandedUrl":"https://twitter.com/SolanaGun/status/1737095410454569067/photo/1","url":"https://pbs.twimg.com/media/GBtnDK4bEAAGL3y.jpg","width":1024,"height":1024}],"isEdited":false,"isStaleEdit":false},"isEdited":true,"isStaleEdit":false,"previous_counts":{"favorite_count":0,"quote_count":0,"reply_count":2,"retweet_count":0},"note_tweet":{"id":"Tm90ZVR3ZWV0UmVzdWx0czoxNzM3MTEyNDgwNzc2OTQ1NjY0"}},{"__typename":"Tweet","lang":"en","favorite_count":18,"created_at":"2023-12-24T19:37:48.000Z","display_text_range":[0,281],"entities":{"hashtags":[],"urls":[],"user_mentions":[{"id_str":"1657706221443637249","indices":[23,35],"name":"Stark Inu","screen_name":"starkinucom"}],"symbols":[{"indices":[236,240],"text":"ETH"},{"indices":[244,249],"text":"STRK"}]},"id_str":"1739007484759847364","text":"Gmeow Santa Mulan aped @starkinucom on Starknet and wanna split some alfa \n\n- Starknet v0.13.0 upgrade on is planning to happen on 1/10. This upgrade is important for the Starknet Ecosystem as it’s expected to change its gas token from $ETH to $STRK\n\n- Inu Good meme, and starkinu…","user":{"id_str":"1340668185154969600","name":"Restaked Mulan 木兰 ラン","profile_image_url_https":"https://pbs.twimg.com/profile_images/1727680464549535744/NpdzUIDv_normal.jpg","screen_name":"Mulan0x","verified":false,"is_blue_verified":false,"profile_image_shape":"Circle"},"edit_control":{"edit_tweet_ids":["1739007484759847364"],"editable_until_msecs":"1703450268000","is_edit_eligible":true,"edits_remaining":"5"},"conversation_count":1,"news_action_type":"conversation","isEdited":false,"isStaleEdit":false,"note_tweet":{"id":"Tm90ZVR3ZWV0UmVzdWx0czoxNzM5MDA3NDg0NjY3NTI3MTY4"}},{"__typename":"Tweet","lang":"en","favorite_count":54,"created_at":"2023-10-23T16:31:32.000Z","display_text_range":[0,274],"entities":{"hashtags":[],"urls":[],"user_mentions":[],"symbols":[]},"id_str":"1716492562972790956","text":"Introducing Bullpen Daily Digest\n\nA free, public Telegram channel densely packed with hand-curated alpha\n\nWhat makes Bullpen Daily Digest different?\n🚀Extremely crypto-native (high-signal)\n⏱️Takes 1 minute to scan through (low-noise)\n📈Potential 1,000x insights (asymmetric…","user":{"id_str":"1075289928932573184","name":"Sal Qadir | Bullpen.fi","profile_image_url_https":"https://pbs.twimg.com/profile_images/1603860016435437568/Fb9USa2h_normal.png","screen_name":"salxyz","verified":false,"is_blue_verified":true,"profile_image_shape":"Hexagon"},"edit_control":{"edit_tweet_ids":["1716492562972790956"],"editable_until_msecs":"1698082292000","is_edit_eligible":true,"edits_remaining":"5"},"conversation_count":13,"news_action_type":"conversation","isEdited":false,"isStaleEdit":false,"note_tweet":{"id":"Tm90ZVR3ZWV0UmVzdWx0czoxNzE2NDkyNTYyNTUzMzYwMzg3"}},{"__typename":"Tweet","lang":"en","favorite_count":2,"possibly_sensitive":false,"created_at":"2023-10-25T10:43:12.000Z","display_text_range":[0,266],"entities":{"hashtags":[{"indices":[61,65],"text":"BTC"}],"urls":[{"display_url":"twitter.com/Ronniek811/sta…","expanded_url":"https://twitter.com/Ronniek811/status/1712089895047667940","indices":[25,48],"url":"https://t.co/0xaCUvs44J"},{"display_url":"i.bybit.com/ab1i5oSZ?actio…","expanded_url":"https://i.bybit.com/ab1i5oSZ?action=inviteToCopy","indices":[160,183],"url":"https://t.co/9os7HPSOxW"}],"user_mentions":[],"symbols":[],"media":[{"display_url":"pic.twitter.com/K8S91oT118","expanded_url":"https://twitter.com/Ronniek811/status/1717129675993194985/photo/1","indices":[267,290],"url":"https://t.co/K8S91oT118"}]},"id_str":"1717129675993194985","text":"This is USDTDOM chart\nOP:https://t.co/0xaCUvs44J\n\nSeems like #BTC is on 48K path. Check chart for Notes\nBTC RETEST reloading. Follow my COPY TRADE\n\nCOPY TRADE: https://t.co/9os7HPSOxW\n\nDrop to PINK channel will have ALT pump!!! hence follow my profile for calls.\nNFA https://t.co/K8S91oT118","user":{"id_str":"1405578612326076419","name":"Ronniek81","profile_image_url_https":"https://pbs.twimg.com/profile_images/1502879306535497731/WyngCKEF_normal.png","screen_name":"Ronniek811","verified":false,"is_blue_verified":false,"profile_image_shape":"Circle"},"edit_control":{"edit_tweet_ids":["1717129675993194985"],"editable_until_msecs":"1698234192000","is_edit_eligible":true,"edits_remaining":"5"},"mediaDetails":[{"display_url":"pic.twitter.com/K8S91oT118","expanded_url":"https://twitter.com/Ronniek811/status/1717129675993194985/photo/1","ext_media_availability":{"status":"Available"},"indices":[267,290],"media_url_https":"https://pbs.twimg.com/media/F9RzOrSa8AATpeL.jpg","original_info":{"height":1153,"width":3568,"focus_rects":[{"x":1509,"y":0,"w":2059,"h":1153},{"x":2415,"y":0,"w":1153,"h":1153},{"x":2557,"y":0,"w":1011,"h":1153},{"x":2834,"y":0,"w":577,"h":1153},{"x":0,"y":0,"w":3568,"h":1153}]},"sizes":{"large":{"h":662,"resize":"fit","w":2048},"medium":{"h":388,"resize":"fit","w":1200},"small":{"h":220,"resize":"fit","w":680},"thumb":{"h":150,"resize":"crop","w":150}},"type":"photo","url":"https://t.co/K8S91oT118"},{"display_url":"pic.twitter.com/K8S91oT118","expanded_url":"https://twitter.com/Ronniek811/status/1717129675993194985/photo/1","ext_media_availability":{"status":"Available"},"indices":[267,290],"media_url_https":"https://pbs.twimg.com/media/F9R369WacAAuykW.jpg","original_info":{"height":1105,"width":2857,"focus_rects":[{"x":884,"y":0,"w":1973,"h":1105},{"x":1515,"y":0,"w":1105,"h":1105},{"x":1583,"y":0,"w":969,"h":1105},{"x":1791,"y":0,"w":553,"h":1105},{"x":0,"y":0,"w":2857,"h":1105}]},"sizes":{"large":{"h":792,"resize":"fit","w":2048},"medium":{"h":464,"resize":"fit","w":1200},"small":{"h":263,"resize":"fit","w":680},"thumb":{"h":150,"resize":"crop","w":150}},"type":"photo","url":"https://t.co/K8S91oT118"}],"photos":[{"backgroundColor":{"red":204,"green":214,"blue":221},"cropCandidates":[{"x":1509,"y":0,"w":2059,"h":1153},{"x":2415,"y":0,"w":1153,"h":1153},{"x":2557,"y":0,"w":1011,"h":1153},{"x":2834,"y":0,"w":577,"h":1153},{"x":0,"y":0,"w":3568,"h":1153}],"expandedUrl":"https://twitter.com/Ronniek811/status/1717129675993194985/photo/1","url":"https://pbs.twimg.com/media/F9RzOrSa8AATpeL.jpg","width":3568,"height":1153},{"backgroundColor":{"red":204,"green":214,"blue":221},"cropCandidates":[{"x":884,"y":0,"w":1973,"h":1105},{"x":1515,"y":0,"w":1105,"h":1105},{"x":1583,"y":0,"w":969,"h":1105},{"x":1791,"y":0,"w":553,"h":1105},{"x":0,"y":0,"w":2857,"h":1105}],"expandedUrl":"https://twitter.com/Ronniek811/status/1717129675993194985/photo/1","url":"https://pbs.twimg.com/media/F9R369WacAAuykW.jpg","width":2857,"height":1105}],"conversation_count":0,"news_action_type":"conversation","quoted_tweet":{"lang":"en","reply_count":1,"retweet_count":0,"favorite_count":1,"possibly_sensitive":false,"created_at":"2023-10-11T12:56:54.000Z","display_text_range":[0,280],"entities":{"hashtags":[{"indices":[0,4],"text":"BTC"},{"indices":[152,160],"text":"Bitcoin"}],"urls":[{"display_url":"i.bybit.com/ab1i5oSZ?actio…","expanded_url":"https://i.bybit.com/ab1i5oSZ?action=inviteToCopy","indices":[23,46],"url":"https://t.co/9os7HPSOxW"}],"user_mentions":[],"symbols":[],"media":[{"display_url":"pic.twitter.com/M0sALIfpA1","expanded_url":"https://twitter.com/Ronniek811/status/1712089895047667940/photo/1","indices":[281,304],"url":"https://t.co/M0sALIfpA1"}]},"id_str":"1712089895047667940","text":"#BTC\nBYBIT COPY TRADE: https://t.co/9os7HPSOxW\n\nUSDT DOM chart has been in the wedge and IMO is ready for a leg down after RETEST before deciding final #Bitcoin direction.\n\nThis leg down will see some ALT pumps!!! hence check my profile for some calls.\n\nCheck chart for Notes. NFA https://t.co/M0sALIfpA1","user":{"id_str":"1405578612326076419","name":"Ronniek81","profile_image_url_https":"https://pbs.twimg.com/profile_images/1502879306535497731/WyngCKEF_normal.png","screen_name":"Ronniek811","verified":false,"is_blue_verified":false,"profile_image_shape":"Circle"},"edit_control":{"edit_tweet_ids":["1712089895047667940"],"editable_until_msecs":"1697032614000","is_edit_eligible":true,"edits_remaining":"5"},"mediaDetails":[{"display_url":"pic.twitter.com/M0sALIfpA1","expanded_url":"https://twitter.com/Ronniek811/status/1712089895047667940/photo/1","ext_media_availability":{"status":"Available"},"indices":[281,304],"media_url_https":"https://pbs.twimg.com/media/F8KOOSEaEAArlX7.jpg","original_info":{"height":1124,"width":4096,"focus_rects":[{"x":2089,"y":0,"w":2007,"h":1124},{"x":2605,"y":0,"w":1124,"h":1124},{"x":2674,"y":0,"w":986,"h":1124},{"x":2886,"y":0,"w":562,"h":1124},{"x":0,"y":0,"w":4096,"h":1124}]},"sizes":{"large":{"h":562,"resize":"fit","w":2048},"medium":{"h":329,"resize":"fit","w":1200},"small":{"h":187,"resize":"fit","w":680},"thumb":{"h":150,"resize":"crop","w":150}},"type":"photo","url":"https://t.co/M0sALIfpA1"},{"display_url":"pic.twitter.com/M0sALIfpA1","expanded_url":"https://twitter.com/Ronniek811/status/1712089895047667940/photo/1","ext_media_availability":{"status":"Available"},"indices":[281,304],"media_url_https":"https://pbs.twimg.com/media/F8KPNpRboAAX9kz.jpg","original_info":{"height":1061,"width":2772,"focus_rects":[{"x":785,"y":0,"w":1895,"h":1061},{"x":1202,"y":0,"w":1061,"h":1061},{"x":1267,"y":0,"w":931,"h":1061},{"x":1467,"y":0,"w":531,"h":1061},{"x":0,"y":0,"w":2772,"h":1061}]},"sizes":{"large":{"h":784,"resize":"fit","w":2048},"medium":{"h":459,"resize":"fit","w":1200},"small":{"h":260,"resize":"fit","w":680},"thumb":{"h":150,"resize":"crop","w":150}},"type":"photo","url":"https://t.co/M0sALIfpA1"}],"photos":[{"backgroundColor":{"red":204,"green":214,"blue":221},"cropCandidates":[{"x":2089,"y":0,"w":2007,"h":1124},{"x":2605,"y":0,"w":1124,"h":1124},{"x":2674,"y":0,"w":986,"h":1124},{"x":2886,"y":0,"w":562,"h":1124},{"x":0,"y":0,"w":4096,"h":1124}],"expandedUrl":"https://twitter.com/Ronniek811/status/1712089895047667940/photo/1","url":"https://pbs.twimg.com/media/F8KOOSEaEAArlX7.jpg","width":4096,"height":1124},{"backgroundColor":{"red":204,"green":214,"blue":221},"cropCandidates":[{"x":785,"y":0,"w":1895,"h":1061},{"x":1202,"y":0,"w":1061,"h":1061},{"x":1267,"y":0,"w":931,"h":1061},{"x":1467,"y":0,"w":531,"h":1061},{"x":0,"y":0,"w":2772,"h":1061}],"expandedUrl":"https://twitter.com/Ronniek811/status/1712089895047667940/photo/1","url":"https://pbs.twimg.com/media/F8KPNpRboAAX9kz.jpg","width":2772,"height":1061}],"isEdited":false,"isStaleEdit":false},"isEdited":false,"isStaleEdit":false},{"__typename":"Tweet","lang":"en","favorite_count":2,"possibly_sensitive":false,"created_at":"2023-10-24T10:39:46.000Z","display_text_range":[0,272],"entities":{"hashtags":[{"indices":[53,69],"text":"ConstitutionDAO"},{"indices":[172,176],"text":"BTC"}],"urls":[{"display_url":"i.bybit.com/ab1i5oSZ?actio…","expanded_url":"https://i.bybit.com/ab1i5oSZ?action=inviteToCopy","indices":[107,130],"url":"https://t.co/9os7HPSOxW"},{"display_url":"twitter.com/Ronniek811/sta…","expanded_url":"https://twitter.com/Ronniek811/status/1712069805543698872","indices":[147,170],"url":"https://t.co/pXF2cvUouz"}],"user_mentions":[],"symbols":[{"indices":[44,51],"text":"PEOPLE"}],"media":[{"display_url":"pic.twitter.com/o4POSle2Cn","expanded_url":"https://twitter.com/Ronniek811/status/1716766426894331958/photo/1","indices":[273,296],"url":"https://t.co/o4POSle2Cn"}]},"id_str":"1716766426894331958","text":"520% GAINS!\nCongrats to those who followed!\n$PEOPLE (#ConstitutionDAO ) has reached target 2.\n\nCOPY TRADE: https://t.co/9os7HPSOxW\n\nORIGINAL POST: https://t.co/pXF2cvUouz\n\n#BTC  at pivot point but hoping for target 4. \nShow some love! \nFollow, retweet, like, comment. \nNFA https://t.co/o4POSle2Cn","user":{"id_str":"1405578612326076419","name":"Ronniek81","profile_image_url_https":"https://pbs.twimg.com/profile_images/1502879306535497731/WyngCKEF_normal.png","screen_name":"Ronniek811","verified":false,"is_blue_verified":false,"profile_image_shape":"Circle"},"edit_control":{"edit_tweet_ids":["1716766426894331958"],"editable_until_msecs":"1698147586000","is_edit_eligible":true,"edits_remaining":"5"},"mediaDetails":[{"display_url":"pic.twitter.com/o4POSle2Cn","expanded_url":"https://twitter.com/Ronniek811/status/1716766426894331958/photo/1","ext_media_availability":{"status":"Available"},"indices":[273,296],"media_url_https":"https://pbs.twimg.com/media/F9MsvKSa0AAMR8O.jpg","original_info":{"height":1268,"width":922,"focus_rects":[{"x":0,"y":26,"w":922,"h":516},{"x":0,"y":0,"w":922,"h":922},{"x":0,"y":0,"w":922,"h":1051},{"x":0,"y":0,"w":634,"h":1268},{"x":0,"y":0,"w":922,"h":1268}]},"sizes":{"large":{"h":1268,"resize":"fit","w":922},"medium":{"h":1200,"resize":"fit","w":873},"small":{"h":680,"resize":"fit","w":494},"thumb":{"h":150,"resize":"crop","w":150}},"type":"photo","url":"https://t.co/o4POSle2Cn"},{"display_url":"pic.twitter.com/o4POSle2Cn","expanded_url":"https://twitter.com/Ronniek811/status/1716766426894331958/photo/1","ext_media_availability":{"status":"Available"},"indices":[273,296],"media_url_https":"https://pbs.twimg.com/media/F9MtWdxbgAA2uCX.jpg","original_info":{"height":1108,"width":2710,"focus_rects":[{"x":731,"y":0,"w":1979,"h":1108},{"x":1272,"y":0,"w":1108,"h":1108},{"x":1340,"y":0,"w":972,"h":1108},{"x":1549,"y":0,"w":554,"h":1108},{"x":0,"y":0,"w":2710,"h":1108}]},"sizes":{"large":{"h":837,"resize":"fit","w":2048},"medium":{"h":491,"resize":"fit","w":1200},"small":{"h":278,"resize":"fit","w":680},"thumb":{"h":150,"resize":"crop","w":150}},"type":"photo","url":"https://t.co/o4POSle2Cn"}],"photos":[{"backgroundColor":{"red":204,"green":214,"blue":221},"cropCandidates":[{"x":0,"y":26,"w":922,"h":516},{"x":0,"y":0,"w":922,"h":922},{"x":0,"y":0,"w":922,"h":1051},{"x":0,"y":0,"w":634,"h":1268},{"x":0,"y":0,"w":922,"h":1268}],"expandedUrl":"https://twitter.com/Ronniek811/status/1716766426894331958/photo/1","url":"https://pbs.twimg.com/media/F9MsvKSa0AAMR8O.jpg","width":922,"height":1268},{"backgroundColor":{"red":204,"green":214,"blue":221},"cropCandidates":[{"x":731,"y":0,"w":1979,"h":1108},{"x":1272,"y":0,"w":1108,"h":1108},{"x":1340,"y":0,"w":972,"h":1108},{"x":1549,"y":0,"w":554,"h":1108},{"x":0,"y":0,"w":2710,"h":1108}],"expandedUrl":"https://twitter.com/Ronniek811/status/1716766426894331958/photo/1","url":"https://pbs.twimg.com/media/F9MtWdxbgAA2uCX.jpg","width":2710,"height":1108}],"conversation_count":0,"news_action_type":"conversation","quoted_tweet":{"lang":"en","reply_count":1,"retweet_count":0,"favorite_count":1,"possibly_sensitive":false,"created_at":"2023-10-11T11:37:05.000Z","display_text_range":[0,258],"entities":{"hashtags":[{"indices":[50,66],"text":"ConstitutionDAO"},{"indices":[209,213],"text":"BTC"}],"urls":[{"display_url":"i.bybit.com/ab1i5oSZ?actio…","expanded_url":"https://i.bybit.com/ab1i5oSZ?action=inviteToCopy","indices":[12,35],"url":"https://t.co/9os7HPSOxW"}],"user_mentions":[],"symbols":[{"indices":[41,48],"text":"PEOPLE"}],"media":[{"display_url":"pic.twitter.com/utHMRhUgtv","expanded_url":"https://twitter.com/Ronniek811/status/1712069805543698872/photo/1","indices":[259,282],"url":"https://t.co/utHMRhUgtv"}]},"id_str":"1712069805543698872","text":"COPY TRADE: https://t.co/9os7HPSOxW\n\nIMO $PEOPLE (#ConstitutionDAO ) is in this downward trend.\nExpecting a bounce here and then trendbreak to the up!      Nice 100% gains for target 3.\nOfcourse it depends on #BTC move.\nFollow, like, comment and retweet. NFA https://t.co/utHMRhUgtv","user":{"id_str":"1405578612326076419","name":"Ronniek81","profile_image_url_https":"https://pbs.twimg.com/profile_images/1502879306535497731/WyngCKEF_normal.png","screen_name":"Ronniek811","verified":false,"is_blue_verified":false,"profile_image_shape":"Circle"},"edit_control":{"edit_tweet_ids":["1712069805543698872"],"editable_until_msecs":"1697027825000","is_edit_eligible":true,"edits_remaining":"5"},"mediaDetails":[{"display_url":"pic.twitter.com/utHMRhUgtv","expanded_url":"https://twitter.com/Ronniek811/status/1712069805543698872/photo/1","ext_media_availability":{"status":"Available"},"indices":[259,282],"media_url_https":"https://pbs.twimg.com/media/F8JvnAsbIAA2VlR.jpg","original_info":{"height":1081,"width":2169,"focus_rects":[{"x":239,"y":0,"w":1930,"h":1081},{"x":924,"y":0,"w":1081,"h":1081},{"x":990,"y":0,"w":948,"h":1081},{"x":1194,"y":0,"w":541,"h":1081},{"x":0,"y":0,"w":2169,"h":1081}]},"sizes":{"large":{"h":1021,"resize":"fit","w":2048},"medium":{"h":598,"resize":"fit","w":1200},"small":{"h":339,"resize":"fit","w":680},"thumb":{"h":150,"resize":"crop","w":150}},"type":"photo","url":"https://t.co/utHMRhUgtv"}],"photos":[{"backgroundColor":{"red":204,"green":214,"blue":221},"cropCandidates":[{"x":239,"y":0,"w":1930,"h":1081},{"x":924,"y":0,"w":1081,"h":1081},{"x":990,"y":0,"w":948,"h":1081},{"x":1194,"y":0,"w":541,"h":1081},{"x":0,"y":0,"w":2169,"h":1081}],"expandedUrl":"https://twitter.com/Ronniek811/status/1712069805543698872/photo/1","url":"https://pbs.twimg.com/media/F8JvnAsbIAA2VlR.jpg","width":2169,"height":1081}],"isEdited":false,"isStaleEdit":false},"isEdited":false,"isStaleEdit":false},{"__typename":"Tweet","lang":"en","favorite_count":2,"possibly_sensitive":false,"created_at":"2023-10-24T10:33:11.000Z","display_text_range":[0,279],"entities":{"hashtags":[{"indices":[169,173],"text":"BTC"}],"urls":[{"display_url":"i.bybit.com/ab1i5oSZ?actio…","expanded_url":"https://i.bybit.com/ab1i5oSZ?action=inviteToCopy","indices":[104,127],"url":"https://t.co/9os7HPSOxW"},{"display_url":"twitter.com/Ronniek811/sta…","expanded_url":"https://twitter.com/Ronniek811/status/1711699323095007330","indices":[144,167],"url":"https://t.co/eZMuC2SIDg"}],"user_mentions":[{"id_str":"1329587028632219648","indices":[52,68],"name":"Alice","screen_name":"MyNeighborAlice"}],"symbols":[{"indices":[44,50],"text":"ALICE"}],"media":[{"display_url":"pic.twitter.com/veP5Uo2p3T","expanded_url":"https://twitter.com/Ronniek811/status/1716764769989108214/photo/1","indices":[280,303],"url":"https://t.co/veP5Uo2p3T"}]},"id_str":"1716764769989108214","text":"210% GAINS\nCongrats to those who followed! \n$ALICE (@MyNeighborAlice) has reached target 2\n\nCOPY TRADE: https://t.co/9os7HPSOxW\n\nORIGINAL POST: https://t.co/eZMuC2SIDg\n\n#BTC at pivot point but hoping for target 4 to be reached. show some love! Follow, retweet, like, comment. NFA https://t.co/veP5Uo2p3T","user":{"id_str":"1405578612326076419","name":"Ronniek81","profile_image_url_https":"https://pbs.twimg.com/profile_images/1502879306535497731/WyngCKEF_normal.png","screen_name":"Ronniek811","verified":false,"is_blue_verified":false,"profile_image_shape":"Circle"},"edit_control":{"edit_tweet_ids":["1716764769989108214"],"editable_until_msecs":"1698147191000","is_edit_eligible":true,"edits_remaining":"5"},"mediaDetails":[{"display_url":"pic.twitter.com/veP5Uo2p3T","expanded_url":"https://twitter.com/Ronniek811/status/1716764769989108214/photo/1","ext_media_availability":{"status":"Available"},"indices":[280,303],"media_url_https":"https://pbs.twimg.com/media/F9MqXevaUAA7lMl.jpg","original_info":{"height":1268,"width":922,"focus_rects":[{"x":0,"y":752,"w":922,"h":516},{"x":0,"y":346,"w":922,"h":922},{"x":0,"y":217,"w":922,"h":1051},{"x":0,"y":0,"w":634,"h":1268},{"x":0,"y":0,"w":922,"h":1268}]},"sizes":{"large":{"h":1268,"resize":"fit","w":922},"medium":{"h":1200,"resize":"fit","w":873},"small":{"h":680,"resize":"fit","w":494},"thumb":{"h":150,"resize":"crop","w":150}},"type":"photo","url":"https://t.co/veP5Uo2p3T"},{"display_url":"pic.twitter.com/veP5Uo2p3T","expanded_url":"https://twitter.com/Ronniek811/status/1716764769989108214/photo/1","ext_media_availability":{"status":"Available"},"indices":[280,303],"media_url_https":"https://pbs.twimg.com/media/F9MrRQLaIAA4Kbv.jpg","original_info":{"height":1151,"width":2981,"focus_rects":[{"x":463,"y":0,"w":2055,"h":1151},{"x":915,"y":0,"w":1151,"h":1151},{"x":985,"y":0,"w":1010,"h":1151},{"x":1202,"y":0,"w":576,"h":1151},{"x":0,"y":0,"w":2981,"h":1151}]},"sizes":{"large":{"h":791,"resize":"fit","w":2048},"medium":{"h":463,"resize":"fit","w":1200},"small":{"h":263,"resize":"fit","w":680},"thumb":{"h":150,"resize":"crop","w":150}},"type":"photo","url":"https://t.co/veP5Uo2p3T"}],"photos":[{"backgroundColor":{"red":204,"green":214,"blue":221},"cropCandidates":[{"x":0,"y":752,"w":922,"h":516},{"x":0,"y":346,"w":922,"h":922},{"x":0,"y":217,"w":922,"h":1051},{"x":0,"y":0,"w":634,"h":1268},{"x":0,"y":0,"w":922,"h":1268}],"expandedUrl":"https://twitter.com/Ronniek811/status/1716764769989108214/photo/1","url":"https://pbs.twimg.com/media/F9MqXevaUAA7lMl.jpg","width":922,"height":1268},{"backgroundColor":{"red":204,"green":214,"blue":221},"cropCandidates":[{"x":463,"y":0,"w":2055,"h":1151},{"x":915,"y":0,"w":1151,"h":1151},{"x":985,"y":0,"w":1010,"h":1151},{"x":1202,"y":0,"w":576,"h":1151},{"x":0,"y":0,"w":2981,"h":1151}],"expandedUrl":"https://twitter.com/Ronniek811/status/1716764769989108214/photo/1","url":"https://pbs.twimg.com/media/F9MrRQLaIAA4Kbv.jpg","width":2981,"height":1151}],"conversation_count":1,"news_action_type":"conversation","quoted_tweet":{"lang":"en","reply_count":0,"retweet_count":1,"favorite_count":2,"possibly_sensitive":false,"created_at":"2023-10-10T11:04:55.000Z","display_text_range":[0,264],"entities":{"hashtags":[{"indices":[171,179],"text":"Bitcoin"}],"urls":[],"user_mentions":[{"id_str":"1329587028632219648","indices":[12,28],"name":"Alice","screen_name":"MyNeighborAlice"}],"symbols":[{"indices":[4,10],"text":"ALICE"}],"media":[{"display_url":"pic.twitter.com/hDt0bAQ9kq","expanded_url":"https://twitter.com/Ronniek811/status/1711699323095007330/photo/1","indices":[265,288],"url":"https://t.co/hDt0bAQ9kq"}]},"id_str":"1711699323095007330","text":"IMO $ALICE (@MyNeighborAlice) is in this downward trend.  Expecting a bounce here and then trendbreak to the up!  \n\nNice 100% gains for target 6. \n\nOfcourse it depends on #Bitcoin move. NOTES on CHART. \nFollow, like, comment and retweet. NFA Always protect capital https://t.co/hDt0bAQ9kq","user":{"id_str":"1405578612326076419","name":"Ronniek81","profile_image_url_https":"https://pbs.twimg.com/profile_images/1502879306535497731/WyngCKEF_normal.png","screen_name":"Ronniek811","verified":false,"is_blue_verified":false,"profile_image_shape":"Circle"},"edit_control":{"edit_tweet_ids":["1711699323095007330"],"editable_until_msecs":"1696939495000","is_edit_eligible":true,"edits_remaining":"5"},"mediaDetails":[{"display_url":"pic.twitter.com/hDt0bAQ9kq","expanded_url":"https://twitter.com/Ronniek811/status/1711699323095007330/photo/1","ext_media_availability":{"status":"Available"},"indices":[265,288],"media_url_https":"https://pbs.twimg.com/media/F8EssoiaIAApc_L.jpg","original_info":{"height":1155,"width":2289,"focus_rects":[{"x":226,"y":0,"w":2063,"h":1155},{"x":1134,"y":0,"w":1155,"h":1155},{"x":1267,"y":0,"w":1013,"h":1155},{"x":1484,"y":0,"w":578,"h":1155},{"x":0,"y":0,"w":2289,"h":1155}]},"sizes":{"large":{"h":1033,"resize":"fit","w":2048},"medium":{"h":606,"resize":"fit","w":1200},"small":{"h":343,"resize":"fit","w":680},"thumb":{"h":150,"resize":"crop","w":150}},"type":"photo","url":"https://t.co/hDt0bAQ9kq"}],"photos":[{"backgroundColor":{"red":204,"green":214,"blue":221},"cropCandidates":[{"x":226,"y":0,"w":2063,"h":1155},{"x":1134,"y":0,"w":1155,"h":1155},{"x":1267,"y":0,"w":1013,"h":1155},{"x":1484,"y":0,"w":578,"h":1155},{"x":0,"y":0,"w":2289,"h":1155}],"expandedUrl":"https://twitter.com/Ronniek811/status/1711699323095007330/photo/1","url":"https://pbs.twimg.com/media/F8EssoiaIAApc_L.jpg","width":2289,"height":1155}],"isEdited":false,"isStaleEdit":false},"isEdited":false,"isStaleEdit":false},{"__typename":"Tweet","lang":"en","favorite_count":1,"possibly_sensitive":false,"created_at":"2023-10-18T15:30:14.000Z","display_text_range":[0,276],"entities":{"hashtags":[{"indices":[60,64],"text":"BTC"}],"urls":[{"display_url":"i.bybit.com/ab1i5oSZ?actio…","expanded_url":"https://i.bybit.com/ab1i5oSZ?action=inviteToCopy","indices":[31,54],"url":"https://t.co/9os7HPSOxW"}],"user_mentions":[{"id_str":"999947328621395968","indices":[13,28],"name":"Bybit","screen_name":"Bybit_Official"}],"symbols":[],"media":[{"display_url":"pic.twitter.com/GRDmJu78LU","expanded_url":"https://twitter.com/Ronniek811/status/1714665197615587553/photo/1","indices":[277,300],"url":"https://t.co/GRDmJu78LU"}]},"id_str":"1714665197615587553","text":"COPY TRADE: (@Bybit_Official ) https://t.co/9os7HPSOxW\n\nIMO #BTC is in this Massive PINK downward trend.  \n\nDon't get me wrong, I am BULLISH but this is the WORST case scenario for BTC.\nIdeal if we stay above BLUE line.\n\nNOTES on chart. NFA\n\nFollow, like, comment and retweet. https://t.co/GRDmJu78LU","user":{"id_str":"1405578612326076419","name":"Ronniek81","profile_image_url_https":"https://pbs.twimg.com/profile_images/1502879306535497731/WyngCKEF_normal.png","screen_name":"Ronniek811","verified":false,"is_blue_verified":false,"profile_image_shape":"Circle"},"edit_control":{"edit_tweet_ids":["1714665197615587553"],"editable_until_msecs":"1697646614000","is_edit_eligible":true,"edits_remaining":"5"},"mediaDetails":[{"display_url":"pic.twitter.com/GRDmJu78LU","expanded_url":"https://twitter.com/Ronniek811/status/1714665197615587553/photo/1","ext_media_availability":{"status":"Available"},"indices":[277,300],"media_url_https":"https://pbs.twimg.com/media/F8u09FpasAADk_t.jpg","original_info":{"height":1080,"width":4094,"focus_rects":[{"x":2165,"y":0,"w":1929,"h":1080},{"x":3014,"y":0,"w":1080,"h":1080},{"x":3147,"y":0,"w":947,"h":1080},{"x":3516,"y":0,"w":540,"h":1080},{"x":0,"y":0,"w":4094,"h":1080}]},"sizes":{"large":{"h":540,"resize":"fit","w":2048},"medium":{"h":317,"resize":"fit","w":1200},"small":{"h":179,"resize":"fit","w":680},"thumb":{"h":150,"resize":"crop","w":150}},"type":"photo","url":"https://t.co/GRDmJu78LU"}],"photos":[{"backgroundColor":{"red":204,"green":214,"blue":221},"cropCandidates":[{"x":2165,"y":0,"w":1929,"h":1080},{"x":3014,"y":0,"w":1080,"h":1080},{"x":3147,"y":0,"w":947,"h":1080},{"x":3516,"y":0,"w":540,"h":1080},{"x":0,"y":0,"w":4094,"h":1080}],"expandedUrl":"https://twitter.com/Ronniek811/status/1714665197615587553/photo/1","url":"https://pbs.twimg.com/media/F8u09FpasAADk_t.jpg","width":4094,"height":1080}],"conversation_count":0,"news_action_type":"conversation","isEdited":false,"isStaleEdit":false},{"__typename":"Tweet","lang":"en","favorite_count":3,"possibly_sensitive":false,"created_at":"2023-10-15T13:36:09.000Z","display_text_range":[0,280],"entities":{"hashtags":[{"indices":[0,4],"text":"BTC"}],"urls":[{"display_url":"i.bybit.com/ab1i5oSZ?actio…","expanded_url":"https://i.bybit.com/ab1i5oSZ?action=inviteToCopy","indices":[43,66],"url":"https://t.co/9os7HPSOxW"},{"display_url":"twitter.com/Ronniek811/sta…","expanded_url":"https://twitter.com/Ronniek811/status/1712089895047667940","indices":[147,170],"url":"https://t.co/0xaCUvs44J"}],"user_mentions":[{"id_str":"999947328621395968","indices":[14,29],"name":"Bybit","screen_name":"Bybit_Official"}],"symbols":[],"media":[{"display_url":"pic.twitter.com/1wZ8ZrBOn4","expanded_url":"https://twitter.com/Ronniek811/status/1713549324955853274/photo/1","indices":[281,304],"url":"https://t.co/1wZ8ZrBOn4"}]},"id_str":"1713549324955853274","text":"#BTC \n\nBYBIT (@Bybit_Official) COPY TRADE: https://t.co/9os7HPSOxW\n\nThis is a Zoomed in version of the previous chart of USDT DOM.\nPrevious chart: https://t.co/0xaCUvs44J\n\nRSI also shows retest looming. \nA small leg down and then BTC pump again.\nCheck my profile for ALT calls\nNFA https://t.co/1wZ8ZrBOn4","user":{"id_str":"1405578612326076419","name":"Ronniek81","profile_image_url_https":"https://pbs.twimg.com/profile_images/1502879306535497731/WyngCKEF_normal.png","screen_name":"Ronniek811","verified":false,"is_blue_verified":false,"profile_image_shape":"Circle"},"edit_control":{"edit_tweet_ids":["1713549324955853274"],"editable_until_msecs":"1697380569000","is_edit_eligible":true,"edits_remaining":"5"},"mediaDetails":[{"display_url":"pic.twitter.com/1wZ8ZrBOn4","expanded_url":"https://twitter.com/Ronniek811/status/1713549324955853274/photo/1","ext_media_availability":{"status":"Available"},"indices":[281,304],"media_url_https":"https://pbs.twimg.com/media/F8e_S51bkAAACic.jpg","original_info":{"height":1029,"width":1964,"focus_rects":[{"x":63,"y":0,"w":1838,"h":1029},{"x":468,"y":0,"w":1029,"h":1029},{"x":531,"y":0,"w":903,"h":1029},{"x":725,"y":0,"w":515,"h":1029},{"x":0,"y":0,"w":1964,"h":1029}]},"sizes":{"large":{"h":1029,"resize":"fit","w":1964},"medium":{"h":629,"resize":"fit","w":1200},"small":{"h":356,"resize":"fit","w":680},"thumb":{"h":150,"resize":"crop","w":150}},"type":"photo","url":"https://t.co/1wZ8ZrBOn4"}],"photos":[{"backgroundColor":{"red":204,"green":214,"blue":221},"cropCandidates":[{"x":63,"y":0,"w":1838,"h":1029},{"x":468,"y":0,"w":1029,"h":1029},{"x":531,"y":0,"w":903,"h":1029},{"x":725,"y":0,"w":515,"h":1029},{"x":0,"y":0,"w":1964,"h":1029}],"expandedUrl":"https://twitter.com/Ronniek811/status/1713549324955853274/photo/1","url":"https://pbs.twimg.com/media/F8e_S51bkAAACic.jpg","width":1964,"height":1029}],"conversation_count":0,"news_action_type":"conversation","quoted_tweet":{"lang":"en","reply_count":1,"retweet_count":0,"favorite_count":1,"possibly_sensitive":false,"created_at":"2023-10-11T12:56:54.000Z","display_text_range":[0,280],"entities":{"hashtags":[{"indices":[0,4],"text":"BTC"},{"indices":[152,160],"text":"Bitcoin"}],"urls":[{"display_url":"i.bybit.com/ab1i5oSZ?actio…","expanded_url":"https://i.bybit.com/ab1i5oSZ?action=inviteToCopy","indices":[23,46],"url":"https://t.co/9os7HPSOxW"}],"user_mentions":[],"symbols":[],"media":[{"display_url":"pic.twitter.com/M0sALIfpA1","expanded_url":"https://twitter.com/Ronniek811/status/1712089895047667940/photo/1","indices":[281,304],"url":"https://t.co/M0sALIfpA1"}]},"id_str":"1712089895047667940","text":"#BTC\nBYBIT COPY TRADE: https://t.co/9os7HPSOxW\n\nUSDT DOM chart has been in the wedge and IMO is ready for a leg down after RETEST before deciding final #Bitcoin direction.\n\nThis leg down will see some ALT pumps!!! hence check my profile for some calls.\n\nCheck chart for Notes. NFA https://t.co/M0sALIfpA1","user":{"id_str":"1405578612326076419","name":"Ronniek81","profile_image_url_https":"https://pbs.twimg.com/profile_images/1502879306535497731/WyngCKEF_normal.png","screen_name":"Ronniek811","verified":false,"is_blue_verified":false,"profile_image_shape":"Circle"},"edit_control":{"edit_tweet_ids":["1712089895047667940"],"editable_until_msecs":"1697032614000","is_edit_eligible":true,"edits_remaining":"5"},"mediaDetails":[{"display_url":"pic.twitter.com/M0sALIfpA1","expanded_url":"https://twitter.com/Ronniek811/status/1712089895047667940/photo/1","ext_media_availability":{"status":"Available"},"indices":[281,304],"media_url_https":"https://pbs.twimg.com/media/F8KOOSEaEAArlX7.jpg","original_info":{"height":1124,"width":4096,"focus_rects":[{"x":2089,"y":0,"w":2007,"h":1124},{"x":2605,"y":0,"w":1124,"h":1124},{"x":2674,"y":0,"w":986,"h":1124},{"x":2886,"y":0,"w":562,"h":1124},{"x":0,"y":0,"w":4096,"h":1124}]},"sizes":{"large":{"h":562,"resize":"fit","w":2048},"medium":{"h":329,"resize":"fit","w":1200},"small":{"h":187,"resize":"fit","w":680},"thumb":{"h":150,"resize":"crop","w":150}},"type":"photo","url":"https://t.co/M0sALIfpA1"},{"display_url":"pic.twitter.com/M0sALIfpA1","expanded_url":"https://twitter.com/Ronniek811/status/1712089895047667940/photo/1","ext_media_availability":{"status":"Available"},"indices":[281,304],"media_url_https":"https://pbs.twimg.com/media/F8KPNpRboAAX9kz.jpg","original_info":{"height":1061,"width":2772,"focus_rects":[{"x":785,"y":0,"w":1895,"h":1061},{"x":1202,"y":0,"w":1061,"h":1061},{"x":1267,"y":0,"w":931,"h":1061},{"x":1467,"y":0,"w":531,"h":1061},{"x":0,"y":0,"w":2772,"h":1061}]},"sizes":{"large":{"h":784,"resize":"fit","w":2048},"medium":{"h":459,"resize":"fit","w":1200},"small":{"h":260,"resize":"fit","w":680},"thumb":{"h":150,"resize":"crop","w":150}},"type":"photo","url":"https://t.co/M0sALIfpA1"}],"photos":[{"backgroundColor":{"red":204,"green":214,"blue":221},"cropCandidates":[{"x":2089,"y":0,"w":2007,"h":1124},{"x":2605,"y":0,"w":1124,"h":1124},{"x":2674,"y":0,"w":986,"h":1124},{"x":2886,"y":0,"w":562,"h":1124},{"x":0,"y":0,"w":4096,"h":1124}],"expandedUrl":"https://twitter.com/Ronniek811/status/1712089895047667940/photo/1","url":"https://pbs.twimg.com/media/F8KOOSEaEAArlX7.jpg","width":4096,"height":1124},{"backgroundColor":{"red":204,"green":214,"blue":221},"cropCandidates":[{"x":785,"y":0,"w":1895,"h":1061},{"x":1202,"y":0,"w":1061,"h":1061},{"x":1267,"y":0,"w":931,"h":1061},{"x":1467,"y":0,"w":531,"h":1061},{"x":0,"y":0,"w":2772,"h":1061}],"expandedUrl":"https://twitter.com/Ronniek811/status/1712089895047667940/photo/1","url":"https://pbs.twimg.com/media/F8KPNpRboAAX9kz.jpg","width":2772,"height":1061}],"isEdited":false,"isStaleEdit":false},"isEdited":false,"isStaleEdit":false},{"__typename":"Tweet","lang":"en","favorite_count":2,"possibly_sensitive":false,"created_at":"2023-10-13T13:15:54.000Z","display_text_range":[0,252],"entities":{"hashtags":[{"indices":[201,205],"text":"BTC"}],"urls":[{"display_url":"i.bybit.com/ab1i5oSZ?actio…","expanded_url":"https://i.bybit.com/ab1i5oSZ?action=inviteToCopy","indices":[12,35],"url":"https://t.co/9os7HPSOxW"}],"user_mentions":[{"id_str":"2235729541","indices":[48,57],"name":"Dogecoin","screen_name":"dogecoin"}],"symbols":[{"indices":[41,46],"text":"DOGE"}],"media":[{"display_url":"pic.twitter.com/m3xXxmFRiv","expanded_url":"https://twitter.com/Ronniek811/status/1712819450083414191/photo/1","indices":[253,276],"url":"https://t.co/m3xXxmFRiv"}]},"id_str":"1712819450083414191","text":"COPY TRADE: https://t.co/9os7HPSOxW\n\nIMO $DOGE (@dogecoin ) is in this downward trend.\n\nExpecting a bounce here and then trendbreak to the up!      Nice 50% gains for target 3. \nOfcourse it depends on #BTC move. \nFollow, like, comment and retweet. \nNFA https://t.co/m3xXxmFRiv","user":{"id_str":"1405578612326076419","name":"Ronniek81","profile_image_url_https":"https://pbs.twimg.com/profile_images/1502879306535497731/WyngCKEF_normal.png","screen_name":"Ronniek811","verified":false,"is_blue_verified":false,"profile_image_shape":"Circle"},"edit_control":{"edit_tweet_ids":["1712819450083414191"],"editable_until_msecs":"1697206554000","is_edit_eligible":true,"edits_remaining":"5"},"mediaDetails":[{"display_url":"pic.twitter.com/m3xXxmFRiv","expanded_url":"https://twitter.com/Ronniek811/status/1712819450083414191/photo/1","ext_media_availability":{"status":"Available"},"indices":[253,276],"media_url_https":"https://pbs.twimg.com/media/F8UmXBda8AAGKc2.jpg","original_info":{"height":1148,"width":3080,"focus_rects":[{"x":1030,"y":0,"w":2050,"h":1148},{"x":1813,"y":0,"w":1148,"h":1148},{"x":1884,"y":0,"w":1007,"h":1148},{"x":2100,"y":0,"w":574,"h":1148},{"x":0,"y":0,"w":3080,"h":1148}]},"sizes":{"large":{"h":763,"resize":"fit","w":2048},"medium":{"h":447,"resize":"fit","w":1200},"small":{"h":253,"resize":"fit","w":680},"thumb":{"h":150,"resize":"crop","w":150}},"type":"photo","url":"https://t.co/m3xXxmFRiv"}],"photos":[{"backgroundColor":{"red":204,"green":214,"blue":221},"cropCandidates":[{"x":1030,"y":0,"w":2050,"h":1148},{"x":1813,"y":0,"w":1148,"h":1148},{"x":1884,"y":0,"w":1007,"h":1148},{"x":2100,"y":0,"w":574,"h":1148},{"x":0,"y":0,"w":3080,"h":1148}],"expandedUrl":"https://twitter.com/Ronniek811/status/1712819450083414191/photo/1","url":"https://pbs.twimg.com/media/F8UmXBda8AAGKc2.jpg","width":3080,"height":1148}],"conversation_count":0,"news_action_type":"conversation","isEdited":false,"isStaleEdit":false},{"__typename":"Tweet","lang":"en","favorite_count":1,"possibly_sensitive":false,"created_at":"2023-10-11T12:56:54.000Z","display_text_range":[0,280],"entities":{"hashtags":[{"indices":[0,4],"text":"BTC"},{"indices":[152,160],"text":"Bitcoin"}],"urls":[{"display_url":"i.bybit.com/ab1i5oSZ?actio…","expanded_url":"https://i.bybit.com/ab1i5oSZ?action=inviteToCopy","indices":[23,46],"url":"https://t.co/9os7HPSOxW"}],"user_mentions":[],"symbols":[],"media":[{"display_url":"pic.twitter.com/M0sALIfpA1","expanded_url":"https://twitter.com/Ronniek811/status/1712089895047667940/photo/1","indices":[281,304],"url":"https://t.co/M0sALIfpA1"}]},"id_str":"1712089895047667940","text":"#BTC\nBYBIT COPY TRADE: https://t.co/9os7HPSOxW\n\nUSDT DOM chart has been in the wedge and IMO is ready for a leg down after RETEST before deciding final #Bitcoin direction.\n\nThis leg down will see some ALT pumps!!! hence check my profile for some calls.\n\nCheck chart for Notes. NFA https://t.co/M0sALIfpA1","user":{"id_str":"1405578612326076419","name":"Ronniek81","profile_image_url_https":"https://pbs.twimg.com/profile_images/1502879306535497731/WyngCKEF_normal.png","screen_name":"Ronniek811","verified":false,"is_blue_verified":false,"profile_image_shape":"Circle"},"edit_control":{"edit_tweet_ids":["1712089895047667940"],"editable_until_msecs":"1697032614000","is_edit_eligible":true,"edits_remaining":"5"},"mediaDetails":[{"display_url":"pic.twitter.com/M0sALIfpA1","expanded_url":"https://twitter.com/Ronniek811/status/1712089895047667940/photo/1","ext_media_availability":{"status":"Available"},"indices":[281,304],"media_url_https":"https://pbs.twimg.com/media/F8KOOSEaEAArlX7.jpg","original_info":{"height":1124,"width":4096,"focus_rects":[{"x":2089,"y":0,"w":2007,"h":1124},{"x":2605,"y":0,"w":1124,"h":1124},{"x":2674,"y":0,"w":986,"h":1124},{"x":2886,"y":0,"w":562,"h":1124},{"x":0,"y":0,"w":4096,"h":1124}]},"sizes":{"large":{"h":562,"resize":"fit","w":2048},"medium":{"h":329,"resize":"fit","w":1200},"small":{"h":187,"resize":"fit","w":680},"thumb":{"h":150,"resize":"crop","w":150}},"type":"photo","url":"https://t.co/M0sALIfpA1"},{"display_url":"pic.twitter.com/M0sALIfpA1","expanded_url":"https://twitter.com/Ronniek811/status/1712089895047667940/photo/1","ext_media_availability":{"status":"Available"},"indices":[281,304],"media_url_https":"https://pbs.twimg.com/media/F8KPNpRboAAX9kz.jpg","original_info":{"height":1061,"width":2772,"focus_rects":[{"x":785,"y":0,"w":1895,"h":1061},{"x":1202,"y":0,"w":1061,"h":1061},{"x":1267,"y":0,"w":931,"h":1061},{"x":1467,"y":0,"w":531,"h":1061},{"x":0,"y":0,"w":2772,"h":1061}]},"sizes":{"large":{"h":784,"resize":"fit","w":2048},"medium":{"h":459,"resize":"fit","w":1200},"small":{"h":260,"resize":"fit","w":680},"thumb":{"h":150,"resize":"crop","w":150}},"type":"photo","url":"https://t.co/M0sALIfpA1"}],"photos":[{"backgroundColor":{"red":204,"green":214,"blue":221},"cropCandidates":[{"x":2089,"y":0,"w":2007,"h":1124},{"x":2605,"y":0,"w":1124,"h":1124},{"x":2674,"y":0,"w":986,"h":1124},{"x":2886,"y":0,"w":562,"h":1124},{"x":0,"y":0,"w":4096,"h":1124}],"expandedUrl":"https://twitter.com/Ronniek811/status/1712089895047667940/photo/1","url":"https://pbs.twimg.com/media/F8KOOSEaEAArlX7.jpg","width":4096,"height":1124},{"backgroundColor":{"red":204,"green":214,"blue":221},"cropCandidates":[{"x":785,"y":0,"w":1895,"h":1061},{"x":1202,"y":0,"w":1061,"h":1061},{"x":1267,"y":0,"w":931,"h":1061},{"x":1467,"y":0,"w":531,"h":1061},{"x":0,"y":0,"w":2772,"h":1061}],"expandedUrl":"https://twitter.com/Ronniek811/status/1712089895047667940/photo/1","url":"https://pbs.twimg.com/media/F8KPNpRboAAX9kz.jpg","width":2772,"height":1061}],"conversation_count":1,"news_action_type":"conversation","isEdited":false,"isStaleEdit":false},{"__typename":"Tweet","lang":"en","favorite_count":1,"possibly_sensitive":false,"created_at":"2023-10-11T11:37:05.000Z","display_text_range":[0,258],"entities":{"hashtags":[{"indices":[50,66],"text":"ConstitutionDAO"},{"indices":[209,213],"text":"BTC"}],"urls":[{"display_url":"i.bybit.com/ab1i5oSZ?actio…","expanded_url":"https://i.bybit.com/ab1i5oSZ?action=inviteToCopy","indices":[12,35],"url":"https://t.co/9os7HPSOxW"}],"user_mentions":[],"symbols":[{"indices":[41,48],"text":"PEOPLE"}],"media":[{"display_url":"pic.twitter.com/utHMRhUgtv","expanded_url":"https://twitter.com/Ronniek811/status/1712069805543698872/photo/1","indices":[259,282],"url":"https://t.co/utHMRhUgtv"}]},"id_str":"1712069805543698872","text":"COPY TRADE: https://t.co/9os7HPSOxW\n\nIMO $PEOPLE (#ConstitutionDAO ) is in this downward trend.\nExpecting a bounce here and then trendbreak to the up!      Nice 100% gains for target 3.\nOfcourse it depends on #BTC move.\nFollow, like, comment and retweet. NFA https://t.co/utHMRhUgtv","user":{"id_str":"1405578612326076419","name":"Ronniek81","profile_image_url_https":"https://pbs.twimg.com/profile_images/1502879306535497731/WyngCKEF_normal.png","screen_name":"Ronniek811","verified":false,"is_blue_verified":false,"profile_image_shape":"Circle"},"edit_control":{"edit_tweet_ids":["1712069805543698872"],"editable_until_msecs":"1697027825000","is_edit_eligible":true,"edits_remaining":"5"},"mediaDetails":[{"display_url":"pic.twitter.com/utHMRhUgtv","expanded_url":"https://twitter.com/Ronniek811/status/1712069805543698872/photo/1","ext_media_availability":{"status":"Available"},"indices":[259,282],"media_url_https":"https://pbs.twimg.com/media/F8JvnAsbIAA2VlR.jpg","original_info":{"height":1081,"width":2169,"focus_rects":[{"x":239,"y":0,"w":1930,"h":1081},{"x":924,"y":0,"w":1081,"h":1081},{"x":990,"y":0,"w":948,"h":1081},{"x":1194,"y":0,"w":541,"h":1081},{"x":0,"y":0,"w":2169,"h":1081}]},"sizes":{"large":{"h":1021,"resize":"fit","w":2048},"medium":{"h":598,"resize":"fit","w":1200},"small":{"h":339,"resize":"fit","w":680},"thumb":{"h":150,"resize":"crop","w":150}},"type":"photo","url":"https://t.co/utHMRhUgtv"}],"photos":[{"backgroundColor":{"red":204,"green":214,"blue":221},"cropCandidates":[{"x":239,"y":0,"w":1930,"h":1081},{"x":924,"y":0,"w":1081,"h":1081},{"x":990,"y":0,"w":948,"h":1081},{"x":1194,"y":0,"w":541,"h":1081},{"x":0,"y":0,"w":2169,"h":1081}],"expandedUrl":"https://twitter.com/Ronniek811/status/1712069805543698872/photo/1","url":"https://pbs.twimg.com/media/F8JvnAsbIAA2VlR.jpg","width":2169,"height":1081}],"conversation_count":1,"news_action_type":"conversation","isEdited":false,"isStaleEdit":false},{"__typename":"Tweet","lang":"en","favorite_count":2,"possibly_sensitive":false,"created_at":"2023-10-10T13:23:07.000Z","display_text_range":[0,280],"entities":{"hashtags":[{"indices":[29,34],"text":"KAVA"},{"indices":[47,52],"text":"DODO"},{"indices":[66,72],"text":"looks"},{"indices":[85,91],"text":"Alice"},{"indices":[272,280],"text":"Bitcoin"}],"urls":[{"display_url":"i.bybit.com/ab1i5oSZ?actio…","expanded_url":"https://i.bybit.com/ab1i5oSZ?action=inviteToCopy","indices":[180,203],"url":"https://t.co/9os7HPSOxW"},{"display_url":"bybit.com/invite?ref=P2Y…","expanded_url":"https://www.bybit.com/invite?ref=P2YX4V","indices":[226,249],"url":"https://t.co/zjac6Hf7sA"}],"user_mentions":[{"id_str":"1032773383958745088","indices":[35,46],"name":"Kava","screen_name":"KAVA_CHAIN"},{"id_str":"1263479224419012619","indices":[53,65],"name":"DODO 📜","screen_name":"BreederDodo"},{"id_str":"1427557319500472325","indices":[74,84],"name":"LooksRare","screen_name":"LooksRare"},{"id_str":"1329587028632219648","indices":[92,108],"name":"Alice","screen_name":"MyNeighborAlice"}],"symbols":[],"media":[{"display_url":"pic.twitter.com/rDDaAtND5e","expanded_url":"https://twitter.com/Ronniek811/status/1711734104721641479/photo/1","indices":[281,304],"url":"https://t.co/rDDaAtND5e"}]},"id_str":"1711734104721641479","text":"Check Profile for calls. NFA\n#KAVA @KAVA_CHAIN\n#DODO @BreederDodo\n#looks  @LooksRare\n#Alice @MyNeighborAlice\nStarted Copy trade recently\nFollow with trades\n\nBYBIT COPY Trade link: https://t.co/9os7HPSOxW\n\nBYBIT Referral Link: https://t.co/zjac6Hf7sA\nReferral code: P2YX4V\n#Bitcoin https://t.co/rDDaAtND5e","user":{"id_str":"1405578612326076419","name":"Ronniek81","profile_image_url_https":"https://pbs.twimg.com/profile_images/1502879306535497731/WyngCKEF_normal.png","screen_name":"Ronniek811","verified":false,"is_blue_verified":false,"profile_image_shape":"Circle"},"edit_control":{"edit_tweet_ids":["1711734104721641479"],"editable_until_msecs":"1696947787000","is_edit_eligible":true,"edits_remaining":"5"},"mediaDetails":[{"display_url":"pic.twitter.com/rDDaAtND5e","expanded_url":"https://twitter.com/Ronniek811/status/1711734104721641479/photo/1","ext_media_availability":{"status":"Available"},"indices":[281,304],"media_url_https":"https://pbs.twimg.com/media/F8FGze5aIAAfI1C.jpg","original_info":{"height":1155,"width":2289,"focus_rects":[{"x":226,"y":0,"w":2063,"h":1155},{"x":1134,"y":0,"w":1155,"h":1155},{"x":1267,"y":0,"w":1013,"h":1155},{"x":1484,"y":0,"w":578,"h":1155},{"x":0,"y":0,"w":2289,"h":1155}]},"sizes":{"large":{"h":1033,"resize":"fit","w":2048},"medium":{"h":606,"resize":"fit","w":1200},"small":{"h":343,"resize":"fit","w":680},"thumb":{"h":150,"resize":"crop","w":150}},"type":"photo","url":"https://t.co/rDDaAtND5e"},{"display_url":"pic.twitter.com/rDDaAtND5e","expanded_url":"https://twitter.com/Ronniek811/status/1711734104721641479/photo/1","ext_media_availability":{"status":"Available"},"indices":[281,304],"media_url_https":"https://pbs.twimg.com/media/F8FG3xlbkAAcY8p.png","original_info":{"height":409,"width":679,"focus_rects":[{"x":0,"y":29,"w":679,"h":380},{"x":270,"y":0,"w":409,"h":409},{"x":320,"y":0,"w":359,"h":409},{"x":423,"y":0,"w":205,"h":409},{"x":0,"y":0,"w":679,"h":409}]},"sizes":{"large":{"h":409,"resize":"fit","w":679},"medium":{"h":409,"resize":"fit","w":679},"small":{"h":409,"resize":"fit","w":679},"thumb":{"h":150,"resize":"crop","w":150}},"type":"photo","url":"https://t.co/rDDaAtND5e"},{"display_url":"pic.twitter.com/rDDaAtND5e","expanded_url":"https://twitter.com/Ronniek811/status/1711734104721641479/photo/1","ext_media_availability":{"status":"Available"},"indices":[281,304],"media_url_https":"https://pbs.twimg.com/media/F8FG6uIbIAAxVqp.png","original_info":{"height":313,"width":680,"focus_rects":[{"x":61,"y":0,"w":559,"h":313},{"x":184,"y":0,"w":313,"h":313},{"x":203,"y":0,"w":275,"h":313},{"x":262,"y":0,"w":157,"h":313},{"x":0,"y":0,"w":680,"h":313}]},"sizes":{"large":{"h":313,"resize":"fit","w":680},"medium":{"h":313,"resize":"fit","w":680},"small":{"h":313,"resize":"fit","w":680},"thumb":{"h":150,"resize":"crop","w":150}},"type":"photo","url":"https://t.co/rDDaAtND5e"},{"display_url":"pic.twitter.com/rDDaAtND5e","expanded_url":"https://twitter.com/Ronniek811/status/1711734104721641479/photo/1","ext_media_availability":{"status":"Available"},"indices":[281,304],"media_url_https":"https://pbs.twimg.com/media/F8FG9ggawAAyX3v.png","original_info":{"height":342,"width":680,"focus_rects":[{"x":69,"y":0,"w":611,"h":342},{"x":321,"y":0,"w":342,"h":342},{"x":342,"y":0,"w":300,"h":342},{"x":407,"y":0,"w":171,"h":342},{"x":0,"y":0,"w":680,"h":342}]},"sizes":{"large":{"h":342,"resize":"fit","w":680},"medium":{"h":342,"resize":"fit","w":680},"small":{"h":342,"resize":"fit","w":680},"thumb":{"h":150,"resize":"crop","w":150}},"type":"photo","url":"https://t.co/rDDaAtND5e"}],"photos":[{"backgroundColor":{"red":204,"green":214,"blue":221},"cropCandidates":[{"x":226,"y":0,"w":2063,"h":1155},{"x":1134,"y":0,"w":1155,"h":1155},{"x":1267,"y":0,"w":1013,"h":1155},{"x":1484,"y":0,"w":578,"h":1155},{"x":0,"y":0,"w":2289,"h":1155}],"expandedUrl":"https://twitter.com/Ronniek811/status/1711734104721641479/photo/1","url":"https://pbs.twimg.com/media/F8FGze5aIAAfI1C.jpg","width":2289,"height":1155},{"backgroundColor":{"red":204,"green":214,"blue":221},"cropCandidates":[{"x":0,"y":29,"w":679,"h":380},{"x":270,"y":0,"w":409,"h":409},{"x":320,"y":0,"w":359,"h":409},{"x":423,"y":0,"w":205,"h":409},{"x":0,"y":0,"w":679,"h":409}],"expandedUrl":"https://twitter.com/Ronniek811/status/1711734104721641479/photo/1","url":"https://pbs.twimg.com/media/F8FG3xlbkAAcY8p.png","width":679,"height":409},{"backgroundColor":{"red":204,"green":214,"blue":221},"cropCandidates":[{"x":61,"y":0,"w":559,"h":313},{"x":184,"y":0,"w":313,"h":313},{"x":203,"y":0,"w":275,"h":313},{"x":262,"y":0,"w":157,"h":313},{"x":0,"y":0,"w":680,"h":313}],"expandedUrl":"https://twitter.com/Ronniek811/status/1711734104721641479/photo/1","url":"https://pbs.twimg.com/media/F8FG6uIbIAAxVqp.png","width":680,"height":313},{"backgroundColor":{"red":204,"green":214,"blue":221},"cropCandidates":[{"x":69,"y":0,"w":611,"h":342},{"x":321,"y":0,"w":342,"h":342},{"x":342,"y":0,"w":300,"h":342},{"x":407,"y":0,"w":171,"h":342},{"x":0,"y":0,"w":680,"h":342}],"expandedUrl":"https://twitter.com/Ronniek811/status/1711734104721641479/photo/1","url":"https://pbs.twimg.com/media/F8FG9ggawAAyX3v.png","width":680,"height":342}],"conversation_count":0,"news_action_type":"conversation","isEdited":false,"isStaleEdit":false},{"__typename":"Tweet","lang":"en","favorite_count":1,"possibly_sensitive":false,"created_at":"2023-10-10T12:53:54.000Z","display_text_range":[0,265],"entities":{"hashtags":[{"indices":[4,9],"text":"KAVA"},{"indices":[169,177],"text":"Bitcoin"}],"urls":[],"user_mentions":[{"id_str":"1032773383958745088","indices":[11,22],"name":"Kava","screen_name":"KAVA_CHAIN"}],"symbols":[],"media":[{"display_url":"pic.twitter.com/qYKfZPQpiQ","expanded_url":"https://twitter.com/Ronniek811/status/1711726752840741035/photo/1","indices":[266,289],"url":"https://t.co/qYKfZPQpiQ"}]},"id_str":"1711726752840741035","text":"IMO #KAVA (@KAVA_CHAIN) is in this downward trend.  \nExpecting a bounce here and then trendbreak to the up!    \n\nNice 60% gains for target 7.   \n\nOfcourse it depends on #Bitcoin move. \nNOTES on CHART.  \nFollow, like, comment and retweet. NFA \nAlways protect capital https://t.co/qYKfZPQpiQ","user":{"id_str":"1405578612326076419","name":"Ronniek81","profile_image_url_https":"https://pbs.twimg.com/profile_images/1502879306535497731/WyngCKEF_normal.png","screen_name":"Ronniek811","verified":false,"is_blue_verified":false,"profile_image_shape":"Circle"},"edit_control":{"edit_tweet_ids":["1711726752840741035"],"editable_until_msecs":"1696946034000","is_edit_eligible":true,"edits_remaining":"5"},"mediaDetails":[{"display_url":"pic.twitter.com/qYKfZPQpiQ","expanded_url":"https://twitter.com/Ronniek811/status/1711726752840741035/photo/1","ext_media_availability":{"status":"Available"},"indices":[266,289],"media_url_https":"https://pbs.twimg.com/media/F8FGZsoa0AAsWO4.jpg","original_info":{"height":1190,"width":1977,"focus_rects":[{"x":0,"y":83,"w":1977,"h":1107},{"x":787,"y":0,"w":1190,"h":1190},{"x":933,"y":0,"w":1044,"h":1190},{"x":1232,"y":0,"w":595,"h":1190},{"x":0,"y":0,"w":1977,"h":1190}]},"sizes":{"large":{"h":1190,"resize":"fit","w":1977},"medium":{"h":722,"resize":"fit","w":1200},"small":{"h":409,"resize":"fit","w":680},"thumb":{"h":150,"resize":"crop","w":150}},"type":"photo","url":"https://t.co/qYKfZPQpiQ"}],"photos":[{"backgroundColor":{"red":204,"green":214,"blue":221},"cropCandidates":[{"x":0,"y":83,"w":1977,"h":1107},{"x":787,"y":0,"w":1190,"h":1190},{"x":933,"y":0,"w":1044,"h":1190},{"x":1232,"y":0,"w":595,"h":1190},{"x":0,"y":0,"w":1977,"h":1190}],"expandedUrl":"https://twitter.com/Ronniek811/status/1711726752840741035/photo/1","url":"https://pbs.twimg.com/media/F8FGZsoa0AAsWO4.jpg","width":1977,"height":1190}],"conversation_count":0,"news_action_type":"conversation","isEdited":false,"isStaleEdit":false},{"__typename":"Tweet","lang":"en","favorite_count":1,"possibly_sensitive":false,"created_at":"2023-10-10T12:42:51.000Z","display_text_range":[0,265],"entities":{"hashtags":[{"indices":[166,174],"text":"Bitcoin"}],"urls":[],"user_mentions":[{"id_str":"1263479224419012619","indices":[11,23],"name":"DODO 📜","screen_name":"BreederDodo"}],"symbols":[{"indices":[4,9],"text":"DODO"}],"media":[{"display_url":"pic.twitter.com/XQztvZzRVP","expanded_url":"https://twitter.com/Ronniek811/status/1711723971832684709/photo/1","indices":[266,289],"url":"https://t.co/XQztvZzRVP"}]},"id_str":"1711723971832684709","text":"IMO $DODO (@BreederDodo) is in this downward trend.\nExpecting a bounce here and then trendbreak to the up!    \nNice 60% gains for target 5.   \nOfcourse it depends on #Bitcoin move. \n\nNOTES on CHART.  \nFollow, like, comment and retweet. \nNFA. \nAlways protect capital https://t.co/XQztvZzRVP","user":{"id_str":"1405578612326076419","name":"Ronniek81","profile_image_url_https":"https://pbs.twimg.com/profile_images/1502879306535497731/WyngCKEF_normal.png","screen_name":"Ronniek811","verified":false,"is_blue_verified":false,"profile_image_shape":"Circle"},"edit_control":{"edit_tweet_ids":["1711723971832684709"],"editable_until_msecs":"1696945371000","is_edit_eligible":true,"edits_remaining":"5"},"mediaDetails":[{"display_url":"pic.twitter.com/XQztvZzRVP","expanded_url":"https://twitter.com/Ronniek811/status/1711723971832684709/photo/1","ext_media_availability":{"status":"Available"},"indices":[266,289],"media_url_https":"https://pbs.twimg.com/media/F8FDCewa4AAzSCH.jpg","original_info":{"height":1101,"width":2393,"focus_rects":[{"x":213,"y":0,"w":1966,"h":1101},{"x":646,"y":0,"w":1101,"h":1101},{"x":713,"y":0,"w":966,"h":1101},{"x":921,"y":0,"w":551,"h":1101},{"x":0,"y":0,"w":2393,"h":1101}]},"sizes":{"large":{"h":942,"resize":"fit","w":2048},"medium":{"h":552,"resize":"fit","w":1200},"small":{"h":313,"resize":"fit","w":680},"thumb":{"h":150,"resize":"crop","w":150}},"type":"photo","url":"https://t.co/XQztvZzRVP"}],"photos":[{"backgroundColor":{"red":204,"green":214,"blue":221},"cropCandidates":[{"x":213,"y":0,"w":1966,"h":1101},{"x":646,"y":0,"w":1101,"h":1101},{"x":713,"y":0,"w":966,"h":1101},{"x":921,"y":0,"w":551,"h":1101},{"x":0,"y":0,"w":2393,"h":1101}],"expandedUrl":"https://twitter.com/Ronniek811/status/1711723971832684709/photo/1","url":"https://pbs.twimg.com/media/F8FDCewa4AAzSCH.jpg","width":2393,"height":1101}],"conversation_count":0,"news_action_type":"conversation","isEdited":false,"isStaleEdit":false},{"__typename":"Tweet","lang":"en","favorite_count":3,"possibly_sensitive":false,"created_at":"2023-10-10T11:29:30.000Z","display_text_range":[0,262],"entities":{"hashtags":[{"indices":[4,10],"text":"looks"},{"indices":[164,172],"text":"Bitcoin"}],"urls":[],"user_mentions":[{"id_str":"1427557319500472325","indices":[12,22],"name":"LooksRare","screen_name":"LooksRare"}],"symbols":[],"media":[{"display_url":"pic.twitter.com/jgnnFu3zqF","expanded_url":"https://twitter.com/Ronniek811/status/1711705510737854810/photo/1","indices":[263,286],"url":"https://t.co/jgnnFu3zqF"}]},"id_str":"1711705510737854810","text":"IMO #looks (@LooksRare) is in this downward trend.  \nExpecting a bounce here and then trendbreak to the up!\n\nNice 100% gains for target 2.   Ofcourse it depends on #Bitcoin move. \n\nNOTES on CHART.  \nFollow, like, comment and retweet. \nNFA. Always protect capital https://t.co/jgnnFu3zqF","user":{"id_str":"1405578612326076419","name":"Ronniek81","profile_image_url_https":"https://pbs.twimg.com/profile_images/1502879306535497731/WyngCKEF_normal.png","screen_name":"Ronniek811","verified":false,"is_blue_verified":false,"profile_image_shape":"Circle"},"edit_control":{"edit_tweet_ids":["1711705510737854810"],"editable_until_msecs":"1696940970000","is_edit_eligible":true,"edits_remaining":"5"},"mediaDetails":[{"display_url":"pic.twitter.com/jgnnFu3zqF","expanded_url":"https://twitter.com/Ronniek811/status/1711705510737854810/photo/1","ext_media_availability":{"status":"Available"},"indices":[263,286],"media_url_https":"https://pbs.twimg.com/media/F8EzBGCa8AAA8Wb.jpg","original_info":{"height":1072,"width":2132,"focus_rects":[{"x":218,"y":0,"w":1914,"h":1072},{"x":1008,"y":0,"w":1072,"h":1072},{"x":1074,"y":0,"w":940,"h":1072},{"x":1276,"y":0,"w":536,"h":1072},{"x":0,"y":0,"w":2132,"h":1072}]},"sizes":{"large":{"h":1030,"resize":"fit","w":2048},"medium":{"h":603,"resize":"fit","w":1200},"small":{"h":342,"resize":"fit","w":680},"thumb":{"h":150,"resize":"crop","w":150}},"type":"photo","url":"https://t.co/jgnnFu3zqF"}],"photos":[{"backgroundColor":{"red":204,"green":214,"blue":221},"cropCandidates":[{"x":218,"y":0,"w":1914,"h":1072},{"x":1008,"y":0,"w":1072,"h":1072},{"x":1074,"y":0,"w":940,"h":1072},{"x":1276,"y":0,"w":536,"h":1072},{"x":0,"y":0,"w":2132,"h":1072}],"expandedUrl":"https://twitter.com/Ronniek811/status/1711705510737854810/photo/1","url":"https://pbs.twimg.com/media/F8EzBGCa8AAA8Wb.jpg","width":2132,"height":1072}],"conversation_count":0,"news_action_type":"conversation","isEdited":false,"isStaleEdit":false},{"__typename":"Tweet","lang":"en","favorite_count":2,"possibly_sensitive":false,"created_at":"2023-10-10T11:04:55.000Z","display_text_range":[0,264],"entities":{"hashtags":[{"indices":[171,179],"text":"Bitcoin"}],"urls":[],"user_mentions":[{"id_str":"1329587028632219648","indices":[12,28],"name":"Alice","screen_name":"MyNeighborAlice"}],"symbols":[{"indices":[4,10],"text":"ALICE"}],"media":[{"display_url":"pic.twitter.com/hDt0bAQ9kq","expanded_url":"https://twitter.com/Ronniek811/status/1711699323095007330/photo/1","indices":[265,288],"url":"https://t.co/hDt0bAQ9kq"}]},"id_str":"1711699323095007330","text":"IMO $ALICE (@MyNeighborAlice) is in this downward trend.  Expecting a bounce here and then trendbreak to the up!  \n\nNice 100% gains for target 6. \n\nOfcourse it depends on #Bitcoin move. NOTES on CHART. \nFollow, like, comment and retweet. NFA Always protect capital https://t.co/hDt0bAQ9kq","user":{"id_str":"1405578612326076419","name":"Ronniek81","profile_image_url_https":"https://pbs.twimg.com/profile_images/1502879306535497731/WyngCKEF_normal.png","screen_name":"Ronniek811","verified":false,"is_blue_verified":false,"profile_image_shape":"Circle"},"edit_control":{"edit_tweet_ids":["1711699323095007330"],"editable_until_msecs":"1696939495000","is_edit_eligible":true,"edits_remaining":"5"},"mediaDetails":[{"display_url":"pic.twitter.com/hDt0bAQ9kq","expanded_url":"https://twitter.com/Ronniek811/status/1711699323095007330/photo/1","ext_media_availability":{"status":"Available"},"indices":[265,288],"media_url_https":"https://pbs.twimg.com/media/F8EssoiaIAApc_L.jpg","original_info":{"height":1155,"width":2289,"focus_rects":[{"x":226,"y":0,"w":2063,"h":1155},{"x":1134,"y":0,"w":1155,"h":1155},{"x":1267,"y":0,"w":1013,"h":1155},{"x":1484,"y":0,"w":578,"h":1155},{"x":0,"y":0,"w":2289,"h":1155}]},"sizes":{"large":{"h":1033,"resize":"fit","w":2048},"medium":{"h":606,"resize":"fit","w":1200},"small":{"h":343,"resize":"fit","w":680},"thumb":{"h":150,"resize":"crop","w":150}},"type":"photo","url":"https://t.co/hDt0bAQ9kq"}],"photos":[{"backgroundColor":{"red":204,"green":214,"blue":221},"cropCandidates":[{"x":226,"y":0,"w":2063,"h":1155},{"x":1134,"y":0,"w":1155,"h":1155},{"x":1267,"y":0,"w":1013,"h":1155},{"x":1484,"y":0,"w":578,"h":1155},{"x":0,"y":0,"w":2289,"h":1155}],"expandedUrl":"https://twitter.com/Ronniek811/status/1711699323095007330/photo/1","url":"https://pbs.twimg.com/media/F8EssoiaIAApc_L.jpg","width":2289,"height":1155}],"conversation_count":0,"news_action_type":"conversation","isEdited":false,"isStaleEdit":false},{"__typename":"Tweet","lang":"en","favorite_count":2,"possibly_sensitive":false,"created_at":"2023-09-05T15:30:37.000Z","display_text_range":[0,279],"entities":{"hashtags":[{"indices":[4,8],"text":"CRV"},{"indices":[187,195],"text":"Bitcoin"}],"urls":[],"user_mentions":[{"id_str":"1214050967986946051","indices":[10,23],"name":"Curve Finance","screen_name":"CurveFinance"}],"symbols":[],"media":[{"display_url":"pic.twitter.com/1x6BanJJdb","expanded_url":"https://twitter.com/Ronniek811/status/1699082613926002814/photo/1","indices":[280,303],"url":"https://t.co/1x6BanJJdb"}]},"id_str":"1699082613926002814","text":"IMO #CRV (@CurveFinance) is in this downward trend. \nExpecting a bounce off the ORANGE line, if we go down then trendbreak to the up! \nNice 50% gains for target 3. Ofcourse it depends on #Bitcoin move.\nNOTES on CHART.\nFollow, like, comment and retweet. NFA Always protect capital https://t.co/1x6BanJJdb","user":{"id_str":"1405578612326076419","name":"Ronniek81","profile_image_url_https":"https://pbs.twimg.com/profile_images/1502879306535497731/WyngCKEF_normal.png","screen_name":"Ronniek811","verified":false,"is_blue_verified":false,"profile_image_shape":"Circle"},"edit_control":{"edit_tweet_ids":["1699082613926002814"],"editable_until_msecs":"1693931437000","is_edit_eligible":true,"edits_remaining":"5"},"mediaDetails":[{"display_url":"pic.twitter.com/1x6BanJJdb","expanded_url":"https://twitter.com/Ronniek811/status/1699082613926002814/photo/1","ext_media_availability":{"status":"Available"},"indices":[280,303],"media_url_https":"https://pbs.twimg.com/media/F5RakXKbsAAtAoh.jpg","original_info":{"height":1141,"width":2597,"focus_rects":[{"x":559,"y":0,"w":2038,"h":1141},{"x":1456,"y":0,"w":1141,"h":1141},{"x":1596,"y":0,"w":1001,"h":1141},{"x":1851,"y":0,"w":571,"h":1141},{"x":0,"y":0,"w":2597,"h":1141}]},"sizes":{"large":{"h":900,"resize":"fit","w":2048},"medium":{"h":527,"resize":"fit","w":1200},"small":{"h":299,"resize":"fit","w":680},"thumb":{"h":150,"resize":"crop","w":150}},"type":"photo","url":"https://t.co/1x6BanJJdb"}],"photos":[{"backgroundColor":{"red":204,"green":214,"blue":221},"cropCandidates":[{"x":559,"y":0,"w":2038,"h":1141},{"x":1456,"y":0,"w":1141,"h":1141},{"x":1596,"y":0,"w":1001,"h":1141},{"x":1851,"y":0,"w":571,"h":1141},{"x":0,"y":0,"w":2597,"h":1141}],"expandedUrl":"https://twitter.com/Ronniek811/status/1699082613926002814/photo/1","url":"https://pbs.twimg.com/media/F5RakXKbsAAtAoh.jpg","width":2597,"height":1141}],"conversation_count":2,"news_action_type":"conversation","isEdited":false,"isStaleEdit":false},{"__typename":"Tweet","lang":"en","favorite_count":1,"possibly_sensitive":false,"created_at":"2023-07-31T11:22:10.000Z","display_text_range":[0,173],"entities":{"hashtags":[],"urls":[{"display_url":"t.me/scanx_eth","expanded_url":"https://t.me/scanx_eth","indices":[11,34],"url":"https://t.co/j8dMk2NN84"},{"display_url":"xscanx.tech","expanded_url":"https://xscanx.tech/","indices":[42,65],"url":"https://t.co/Sb0W7giOTw"},{"display_url":"twitter.com/ScanX_eth","expanded_url":"https://twitter.com/ScanX_eth","indices":[72,95],"url":"https://t.co/Z59YY6UGRv"},{"display_url":"dexscreener.com/ethereum/0xf98…","expanded_url":"https://dexscreener.com/ethereum/0xf98e1d3a7a32ab17f73a006fc751736a0682fb0d","indices":[136,159],"url":"https://t.co/15xw0ZqESm"}],"user_mentions":[],"symbols":[{"indices":[0,3],"text":"SX"}]},"id_str":"1685974128048885760","text":"$SX \n\nTG : https://t.co/j8dMk2NN84 \nWEB : https://t.co/Sb0W7giOTw\nTWT : https://t.co/Z59YY6UGRv \n\nUtility project ,bot live \n\n5/5 tax \n\nhttps://t.co/15xw0ZqESm\n\nNFA/DYOR 35k","user":{"id_str":"1326953302525800448","name":"kun","profile_image_url_https":"https://pbs.twimg.com/profile_images/1430424182718746625/wVPB2y1f_normal.jpg","screen_name":"crypto_kun7","verified":false,"is_blue_verified":false,"profile_image_shape":"Circle"},"edit_control":{"edit_tweet_ids":["1685974128048885760"],"editable_until_msecs":"1690806130000","is_edit_eligible":true,"edits_remaining":"5"},"conversation_count":0,"news_action_type":"conversation","card":{"card_platform":{"platform":{"audience":{"name":"production"},"device":{"name":"iPhone","version":"13"}}},"name":"summary_large_image","url":"https://t.co/15xw0ZqESm","binding_values":{"app_star_rating":{"string_value":"4.19512","type":"STRING"},"description":{"string_value":"$0.000003819 Scan X (SX) realtime price charts, trading history and info - SX / WETH on Ethereum / Uniswap","type":"STRING"},"domain":{"string_value":"dexscreener.com","type":"STRING"},"app_is_free":{"string_value":"true","type":"STRING"},"site":{"scribe_key":"publisher_id","type":"USER","user_value":{"id_str":"1452480311405727751","path":[]}},"creator":{"type":"USER","user_value":{"id_str":"1452480311405727751","path":[]}},"app_num_ratings":{"string_value":"41","type":"STRING"},"app_price_amount":{"string_value":"0.0","type":"STRING"},"photo_image_full_size_alt_text":{"string_value":"SX / WETH chart","type":"STRING"},"vanity_url":{"scribe_key":"vanity_url","string_value":"dexscreener.com","type":"STRING"},"app_name":{"string_value":"DEX Screener","type":"STRING"},"summary_photo_image_alt_text":{"string_value":"SX / WETH chart","type":"STRING"},"app_id":{"scribe_key":"publisher_app_id","string_value":"1631840457","type":"STRING"},"title":{"string_value":"SX $0.0₅3819 - Scan X / WETH on Ethereum / Uniswap - DEX Screener","type":"STRING"},"app_price_currency":{"string_value":"USD","type":"STRING"},"card_url":{"scribe_key":"card_url","string_value":"https://t.co/15xw0ZqESm","type":"STRING"}}},"isEdited":false,"isStaleEdit":false}]