[{"__typename":"Tweet","lang":"en","favorite_count":1,"possibly_sensitive":false,"created_at":"2023-12-27T08:32:34.000Z","display_text_range":[0,171],"entities":{"hashtags":[],"urls":[],"user_mentions":[{"id_str":"30699048","indices":[20,29],"name":"Shibetoshi Nakamoto","screen_name":"BillyM2k"}],"symbols":[],"media":[{"display_url":"pic.twitter.com/upzjMHBEKq","expanded_url":"https://twitter.com/MrJustmoving1/status/1739927237544038803/photo/1","indices":[172,195],"url":"https://t.co/upzjMHBEKq"}]},"id_str":"1739927237544038803","text":"I'm honored to have @BillyM2k 's BitBlocks in my collection, it was engraved on a RARE satoshi and currently belongs to me. If you need it, please feel free to contact me. https://t.co/upzjMHBEKq","user":{"id_str":"1276466768488419328","name":"moer🧙‍♂️","profile_image_url_https":"https://pbs.twimg.com/profile_images/1627650005308956673/cYRbEBI2_normal.jpg","screen_name":"MrJustmoving1","verified":false,"is_blue_verified":false,"profile_image_shape":"Circle"},"edit_control":{"edit_tweet_ids":["1739927237544038803"],"editable_until_msecs":"1703669554000","is_edit_eligible":true,"edits_remaining":"5"},"mediaDetails":[{"display_url":"pic.twitter.com/upzjMHBEKq","expanded_url":"https://twitter.com/MrJustmoving1/status/1739927237544038803/photo/1","ext_media_availability":{"status":"Available"},"indices":[172,195],"media_url_https":"https://pbs.twimg.com/media/GCV2mTBagAAt555.jpg","original_info":{"height":1200,"width":1200,"focus_rects":[{"x":0,"y":294,"w":1200,"h":672},{"x":0,"y":0,"w":1200,"h":1200},{"x":147,"y":0,"w":1053,"h":1200},{"x":450,"y":0,"w":600,"h":1200},{"x":0,"y":0,"w":1200,"h":1200}]},"sizes":{"large":{"h":1200,"resize":"fit","w":1200},"medium":{"h":1200,"resize":"fit","w":1200},"small":{"h":680,"resize":"fit","w":680},"thumb":{"h":150,"resize":"crop","w":150}},"type":"photo","url":"https://t.co/upzjMHBEKq"}],"photos":[{"backgroundColor":{"red":204,"green":214,"blue":221},"cropCandidates":[{"x":0,"y":294,"w":1200,"h":672},{"x":0,"y":0,"w":1200,"h":1200},{"x":147,"y":0,"w":1053,"h":1200},{"x":450,"y":0,"w":600,"h":1200},{"x":0,"y":0,"w":1200,"h":1200}],"expandedUrl":"https://twitter.com/MrJustmoving1/status/1739927237544038803/photo/1","url":"https://pbs.twimg.com/media/GCV2mTBagAAt555.jpg","width":1200,"height":1200}],"conversation_count":0,"news_action_type":"conversation","quoted_tweet":{"in_reply_to_screen_name":"elonmusk","in_reply_to_status_id_str":"1739892995342664068","in_reply_to_user_id_str":"44196397","lang":"en","reply_count":66,"retweet_count":65,"favorite_count":609,"possibly_sensitive":false,"created_at":"2023-12-27T06:47:49.000Z","display_text_range":[35,270],"entities":{"hashtags":[],"urls":[],"user_mentions":[{"id_str":"44196397","indices":[0,9],"name":"Elon Musk","screen_name":"elonmusk"},{"id_str":"1420609694402433028","indices":[10,25],"name":"Adrian Dittmann","screen_name":"AdrianDittmann"},{"id_str":"1389913567671975937","indices":[26,34],"name":"DogeDesigner","screen_name":"cb_doge"},{"id_str":"30699048","indices":[44,53],"name":"Shibetoshi Nakamoto","screen_name":"BillyM2k"}],"symbols":[],"media":[{"display_url":"pic.twitter.com/AX0bJBRuV0","expanded_url":"https://twitter.com/udiWertheimer/status/1739900877803049393/photo/1","indices":[271,294],"url":"https://t.co/AX0bJBRuV0"}]},"id_str":"1739900877803049393","text":"@elonmusk @AdrianDittmann @cb_doge we did!\n\n@BillyM2k’s jpeg is encoded forever on bitcoin block 783,077\n\ntransaction id ef207ae72e81c068142ab6ea03f2549e8c6edb2e96050ae1616b65ce3347d1edi0\n\n80kb of a smiling doge wizard, stored forever on every bitcoin node on the planet https://t.co/AX0bJBRuV0","user":{"id_str":"14527699","name":"Udi Wertheimer","profile_image_url_https":"https://pbs.twimg.com/profile_images/1713623833788227584/urVICBpq_normal.jpg","screen_name":"udiWertheimer","verified":false,"highlighted_label":{"description":"Taproot Wizards","badge":{"url":"https://pbs.twimg.com/profile_images/1620589771038023680/PewlwV9H_bigger.jpg"},"url":{"url":"https://twitter.com/TaprootWizards","url_type":"DeepLink"},"user_label_type":"BusinessLabel","user_label_display_type":"Badge"},"is_blue_verified":true},"edit_control":{"edit_tweet_ids":["1739900877803049393"],"editable_until_msecs":"1703663269000","is_edit_eligible":false,"edits_remaining":"5"},"mediaDetails":[{"display_url":"pic.twitter.com/AX0bJBRuV0","expanded_url":"https://twitter.com/udiWertheimer/status/1739900877803049393/photo/1","ext_media_availability":{"status":"Available"},"indices":[271,294],"media_url_https":"https://pbs.twimg.com/media/GCVeoJVWgAAdeP6.jpg","original_info":{"height":400,"width":400,"focus_rects":[{"x":0,"y":58,"w":400,"h":224},{"x":0,"y":0,"w":400,"h":400},{"x":49,"y":0,"w":351,"h":400},{"x":150,"y":0,"w":200,"h":400},{"x":0,"y":0,"w":400,"h":400}]},"sizes":{"large":{"h":400,"resize":"fit","w":400},"medium":{"h":400,"resize":"fit","w":400},"small":{"h":400,"resize":"fit","w":400},"thumb":{"h":150,"resize":"crop","w":150}},"type":"photo","url":"https://t.co/AX0bJBRuV0"}],"photos":[{"backgroundColor":{"red":204,"green":214,"blue":221},"cropCandidates":[{"x":0,"y":58,"w":400,"h":224},{"x":0,"y":0,"w":400,"h":400},{"x":49,"y":0,"w":351,"h":400},{"x":150,"y":0,"w":200,"h":400},{"x":0,"y":0,"w":400,"h":400}],"expandedUrl":"https://twitter.com/udiWertheimer/status/1739900877803049393/photo/1","url":"https://pbs.twimg.com/media/GCVeoJVWgAAdeP6.jpg","width":400,"height":400}],"isEdited":false,"isStaleEdit":false},"isEdited":false,"isStaleEdit":false},{"__typename":"Tweet","lang":"en","favorite_count":140,"possibly_sensitive":false,"created_at":"2023-12-30T03:18:53.000Z","display_text_range":[0,168],"entities":{"hashtags":[{"indices":[136,150],"text":"GasHeroLaunch"},{"indices":[151,165],"text":"GasHeroLaunch"}],"urls":[{"display_url":"cryptoslam.io","expanded_url":"https://www.cryptoslam.io/","indices":[111,134],"url":"https://t.co/WZKSFcQbSj"}],"user_mentions":[{"id_str":"1652258679285235712","indices":[26,42],"name":"Gas Hero Official","screen_name":"GasHeroOfficial"}],"symbols":[],"media":[{"display_url":"pic.twitter.com/qbh6Pd1i5i","expanded_url":"https://twitter.com/Mable_Jiang/status/1740935459348623574/photo/1","indices":[166,189],"url":"https://t.co/qbh6Pd1i5i"}]},"id_str":"1740935459348623574","text":"Now you know how hard our @gasheroofficial community tried to Find the Satoshi amongst all the BRC20s huh 🤪🤪🤪\n\nhttps://t.co/WZKSFcQbSj\n\n#GasHeroLaunch #GasHeroLaunch https://t.co/qbh6Pd1i5i","user":{"id_str":"2187170989","name":"Mable Jiang | We're Hiring!","profile_image_url_https":"https://pbs.twimg.com/profile_images/1625647413569675267/jvusunQf_normal.jpg","screen_name":"Mable_Jiang","verified":false,"highlighted_label":{"description":"STEPN | Public Beta Phase VI","badge":{"url":"https://pbs.twimg.com/profile_images/1730501180780912640/9TlfwycE_bigger.png"},"url":{"url":"https://twitter.com/Stepnofficial","url_type":"DeepLink"},"user_label_type":"BusinessLabel","user_label_display_type":"Badge"},"is_blue_verified":true},"edit_control":{"edit_tweet_ids":["1740935459348623574"],"editable_until_msecs":"1703909933000","is_edit_eligible":true,"edits_remaining":"5"},"mediaDetails":[{"display_url":"pic.twitter.com/qbh6Pd1i5i","expanded_url":"https://twitter.com/Mable_Jiang/status/1740935459348623574/photo/1","ext_media_availability":{"status":"Available"},"indices":[166,189],"media_url_https":"https://pbs.twimg.com/media/GCkK7_5bAAA_uQC.jpg","original_info":{"height":1390,"width":1444,"focus_rects":[{"x":0,"y":581,"w":1444,"h":809},{"x":0,"y":0,"w":1390,"h":1390},{"x":0,"y":0,"w":1219,"h":1390},{"x":0,"y":0,"w":695,"h":1390},{"x":0,"y":0,"w":1444,"h":1390}]},"sizes":{"large":{"h":1390,"resize":"fit","w":1444},"medium":{"h":1155,"resize":"fit","w":1200},"small":{"h":655,"resize":"fit","w":680},"thumb":{"h":150,"resize":"crop","w":150}},"type":"photo","url":"https://t.co/qbh6Pd1i5i"}],"photos":[{"backgroundColor":{"red":204,"green":214,"blue":221},"cropCandidates":[{"x":0,"y":581,"w":1444,"h":809},{"x":0,"y":0,"w":1390,"h":1390},{"x":0,"y":0,"w":1219,"h":1390},{"x":0,"y":0,"w":695,"h":1390},{"x":0,"y":0,"w":1444,"h":1390}],"expandedUrl":"https://twitter.com/Mable_Jiang/status/1740935459348623574/photo/1","url":"https://pbs.twimg.com/media/GCkK7_5bAAA_uQC.jpg","width":1444,"height":1390}],"conversation_count":21,"news_action_type":"conversation","isEdited":false,"isStaleEdit":false},{"__typename":"Tweet","lang":"en","favorite_count":273,"possibly_sensitive":false,"created_at":"2022-11-05T20:41:05.000Z","display_text_range":[0,279],"entities":{"hashtags":[{"indices":[167,185],"text":"SatoshiStreetBets"},{"indices":[235,240],"text":"100x"}],"urls":[{"display_url":"SSB.io","expanded_url":"http://SSB.io","indices":[88,111],"url":"https://t.co/k6VYR6NDCr"},{"display_url":"SSB.io","expanded_url":"http://SSB.io","indices":[253,276],"url":"https://t.co/k6VYR6NDCr"}],"user_mentions":[],"symbols":[],"media":[{"display_url":"pic.twitter.com/RdspKHTlhR","expanded_url":"https://twitter.com/SatoshiStBets/status/1588994833942999040/photo/1","indices":[278,301],"url":"https://t.co/RdspKHTlhR"}]},"id_str":"1588994833942999040","text":"Today we're opening up the waitlist to the Satoshi Street Bets price charting platform!\nhttps://t.co/k6VYR6NDCr is the next-generation price charting platform\nmade by #SatoshiStreetBets and is built from the ground up to help you find #100x gems!\n👉Join https://t.co/k6VYR6NDCr👈 https://t.co/RdspKHTlhR","user":{"id_str":"1231601392139329536","name":"SatoshiStreetBets™","profile_image_url_https":"https://pbs.twimg.com/profile_images/1737210454307373056/Fd4aTTN-_normal.jpg","screen_name":"SatoshiStBets","verified":false,"verified_type":"Business","is_blue_verified":true,"profile_image_shape":"Square"},"edit_control":{"edit_tweet_ids":["1588994833942999040"],"editable_until_msecs":"1667682665000","is_edit_eligible":true,"edits_remaining":"5"},"mediaDetails":[{"display_url":"pic.twitter.com/RdspKHTlhR","expanded_url":"https://twitter.com/SatoshiStBets/status/1588994833942999040/photo/1","ext_media_availability":{"status":"Available"},"indices":[278,301],"media_url_https":"https://pbs.twimg.com/media/Fg06X_3WIAoXwMH.jpg","original_info":{"height":1978,"width":2648,"focus_rects":[{"x":0,"y":0,"w":2648,"h":1483},{"x":335,"y":0,"w":1978,"h":1978},{"x":457,"y":0,"w":1735,"h":1978},{"x":830,"y":0,"w":989,"h":1978},{"x":0,"y":0,"w":2648,"h":1978}]},"sizes":{"large":{"h":1530,"resize":"fit","w":2048},"medium":{"h":896,"resize":"fit","w":1200},"small":{"h":508,"resize":"fit","w":680},"thumb":{"h":150,"resize":"crop","w":150}},"type":"photo","url":"https://t.co/RdspKHTlhR"}],"photos":[{"backgroundColor":{"red":204,"green":214,"blue":221},"cropCandidates":[{"x":0,"y":0,"w":2648,"h":1483},{"x":335,"y":0,"w":1978,"h":1978},{"x":457,"y":0,"w":1735,"h":1978},{"x":830,"y":0,"w":989,"h":1978},{"x":0,"y":0,"w":2648,"h":1978}],"expandedUrl":"https://twitter.com/SatoshiStBets/status/1588994833942999040/photo/1","url":"https://pbs.twimg.com/media/Fg06X_3WIAoXwMH.jpg","width":2648,"height":1978}],"conversation_count":78,"news_action_type":"conversation","isEdited":false,"isStaleEdit":false},{"__typename":"Tweet","lang":"en","favorite_count":36,"possibly_sensitive":false,"created_at":"2023-12-06T00:54:51.000Z","display_text_range":[0,278],"entities":{"hashtags":[],"urls":[],"user_mentions":[],"symbols":[],"media":[{"display_url":"pic.twitter.com/Lqln4CvFT2","expanded_url":"https://twitter.com/F4ntast1cMrF0x/status/1732201902681817377/photo/1","indices":[279,302],"url":"https://t.co/Lqln4CvFT2"}]},"id_str":"1732201902681817377","text":"One quality of good art is the variance in its interpretation.\n\nWhen some view The Nakamoto, they see a dank Pepe.\n\nWhen others view The Nakamoto, they see a trading card that brings them back to the PvP games and collecting of their childhood.\n\nBut do you see what I see?\n\nThe… https://t.co/Lqln4CvFT2","user":{"id_str":"1351199080299569154","name":"Mr. Fox 🦊","profile_image_url_https":"https://pbs.twimg.com/profile_images/1671289271720763395/-jbIdHox_normal.jpg","screen_name":"F4ntast1cMrF0x","verified":false,"is_blue_verified":true,"profile_image_shape":"Circle"},"edit_control":{"edit_tweet_ids":["1732201902681817377"],"editable_until_msecs":"1701827691000","is_edit_eligible":true,"edits_remaining":"5"},"mediaDetails":[{"display_url":"pic.twitter.com/Lqln4CvFT2","expanded_url":"https://twitter.com/F4ntast1cMrF0x/status/1732201902681817377/photo/1","ext_media_availability":{"status":"Available"},"indices":[279,302],"media_url_https":"https://pbs.twimg.com/media/GAoEcyEbsAAH-sM.jpg","original_info":{"height":560,"width":400,"focus_rects":[{"x":0,"y":265,"w":400,"h":224},{"x":0,"y":160,"w":400,"h":400},{"x":0,"y":104,"w":400,"h":456},{"x":69,"y":0,"w":280,"h":560},{"x":0,"y":0,"w":400,"h":560}]},"sizes":{"large":{"h":560,"resize":"fit","w":400},"medium":{"h":560,"resize":"fit","w":400},"small":{"h":560,"resize":"fit","w":400},"thumb":{"h":150,"resize":"crop","w":150}},"type":"photo","url":"https://t.co/Lqln4CvFT2"}],"photos":[{"backgroundColor":{"red":204,"green":214,"blue":221},"cropCandidates":[{"x":0,"y":265,"w":400,"h":224},{"x":0,"y":160,"w":400,"h":400},{"x":0,"y":104,"w":400,"h":456},{"x":69,"y":0,"w":280,"h":560},{"x":0,"y":0,"w":400,"h":560}],"expandedUrl":"https://twitter.com/F4ntast1cMrF0x/status/1732201902681817377/photo/1","url":"https://pbs.twimg.com/media/GAoEcyEbsAAH-sM.jpg","width":400,"height":560}],"conversation_count":8,"news_action_type":"conversation","isEdited":false,"isStaleEdit":false,"note_tweet":{"id":"Tm90ZVR3ZWV0UmVzdWx0czoxNzMyMjAxOTAyNTgxMTkwNjU2"}},{"__typename":"Tweet","lang":"en","favorite_count":97,"created_at":"2023-11-27T23:42:50.000Z","display_text_range":[0,281],"entities":{"hashtags":[],"urls":[],"user_mentions":[],"symbols":[]},"id_str":"1729284679054872865","text":"The Nakamoto may be the single greatest work of tokenized art:\n\nit is the combination of crypto’s two most potent memes (Satoshi and Pepe) and opened the door for digitally authentic art to prosper.\n\nBy now you should know that I’m a straight shooter - I am part of no tribe, only…","user":{"id_str":"1351199080299569154","name":"Mr. Fox 🦊","profile_image_url_https":"https://pbs.twimg.com/profile_images/1671289271720763395/-jbIdHox_normal.jpg","screen_name":"F4ntast1cMrF0x","verified":false,"is_blue_verified":true,"profile_image_shape":"Circle"},"edit_control":{"edit_tweet_ids":["1729284679054872865"],"editable_until_msecs":"1701132170000","is_edit_eligible":true,"edits_remaining":"5"},"conversation_count":12,"news_action_type":"conversation","quoted_tweet":{"lang":"tl","reply_count":284,"retweet_count":158,"favorite_count":1647,"possibly_sensitive":false,"created_at":"2023-11-27T23:26:47.000Z","display_text_range":[0,15],"entities":{"hashtags":[],"urls":[],"user_mentions":[],"symbols":[],"media":[{"display_url":"pic.twitter.com/s5EzkzrvAJ","expanded_url":"https://twitter.com/GordonGoner/status/1729280639084683329/photo/1","indices":[15,38],"url":"https://t.co/s5EzkzrvAJ"}]},"id_str":"1729280639084683329","text":"Naka secured 🐸 https://t.co/s5EzkzrvAJ","user":{"id_str":"1362625187489976321","name":"GordonGoner.eth (Wylie Aronow)","profile_image_url_https":"https://pbs.twimg.com/profile_images/1446538671998578692/GxpsJa-l_normal.jpg","screen_name":"GordonGoner","verified":false,"is_blue_verified":true,"profile_image_shape":"Circle"},"edit_control":{"edit_tweet_ids":["1729280639084683329"],"editable_until_msecs":"1701131207000","is_edit_eligible":true,"edits_remaining":"5"},"mediaDetails":[{"display_url":"pic.twitter.com/s5EzkzrvAJ","expanded_url":"https://twitter.com/GordonGoner/status/1729280639084683329/photo/1","ext_media_availability":{"status":"Available"},"indices":[15,38],"media_url_https":"https://pbs.twimg.com/media/F_-gSQGaYAEornK.jpg","original_info":{"height":560,"width":400,"focus_rects":[{"x":0,"y":265,"w":400,"h":224},{"x":0,"y":160,"w":400,"h":400},{"x":0,"y":104,"w":400,"h":456},{"x":69,"y":0,"w":280,"h":560},{"x":0,"y":0,"w":400,"h":560}]},"sizes":{"large":{"h":560,"resize":"fit","w":400},"medium":{"h":560,"resize":"fit","w":400},"small":{"h":560,"resize":"fit","w":400},"thumb":{"h":150,"resize":"crop","w":150}},"type":"photo","url":"https://t.co/s5EzkzrvAJ"}],"photos":[{"backgroundColor":{"red":204,"green":214,"blue":221},"cropCandidates":[{"x":0,"y":265,"w":400,"h":224},{"x":0,"y":160,"w":400,"h":400},{"x":0,"y":104,"w":400,"h":456},{"x":69,"y":0,"w":280,"h":560},{"x":0,"y":0,"w":400,"h":560}],"expandedUrl":"https://twitter.com/GordonGoner/status/1729280639084683329/photo/1","url":"https://pbs.twimg.com/media/F_-gSQGaYAEornK.jpg","width":400,"height":560}],"isEdited":false,"isStaleEdit":false},"isEdited":false,"isStaleEdit":false,"note_tweet":{"id":"Tm90ZVR3ZWV0UmVzdWx0czoxNzI5Mjg0Njc4OTIwNjI2MTc2"}},{"__typename":"Tweet","lang":"en","favorite_count":54,"created_at":"2023-10-23T16:31:32.000Z","display_text_range":[0,274],"entities":{"hashtags":[],"urls":[],"user_mentions":[],"symbols":[]},"id_str":"1716492562972790956","text":"Introducing Bullpen Daily Digest\n\nA free, public Telegram channel densely packed with hand-curated alpha\n\nWhat makes Bullpen Daily Digest different?\n🚀Extremely crypto-native (high-signal)\n⏱️Takes 1 minute to scan through (low-noise)\n📈Potential 1,000x insights (asymmetric…","user":{"id_str":"1075289928932573184","name":"Sal Qadir | Bullpen.fi","profile_image_url_https":"https://pbs.twimg.com/profile_images/1603860016435437568/Fb9USa2h_normal.png","screen_name":"salxyz","verified":false,"is_blue_verified":true,"profile_image_shape":"Hexagon"},"edit_control":{"edit_tweet_ids":["1716492562972790956"],"editable_until_msecs":"1698082292000","is_edit_eligible":true,"edits_remaining":"5"},"conversation_count":13,"news_action_type":"conversation","isEdited":false,"isStaleEdit":false,"note_tweet":{"id":"Tm90ZVR3ZWV0UmVzdWx0czoxNzE2NDkyNTYyNTUzMzYwMzg3"}},{"__typename":"Tweet","lang":"en","favorite_count":5,"possibly_sensitive":false,"created_at":"2023-12-07T11:12:08.000Z","display_text_range":[0,220],"entities":{"hashtags":[{"indices":[103,107],"text":"btc"},{"indices":[108,117],"text":"Ordinals"},{"indices":[118,128],"text":"BTClayer2"},{"indices":[129,146],"text":"LightningNetwork"},{"indices":[147,151],"text":"RGB"}],"urls":[{"display_url":"forms.gle/fKm8okXshTfUQZ…","expanded_url":"https://forms.gle/fKm8okXshTfUQZ579","indices":[171,194],"url":"https://t.co/RTJtjrBNeW"},{"display_url":"cointime.ai/news/satoshi-l…","expanded_url":"https://www.cointime.ai/news/satoshi-lab-will-hold-the-bitcoin-ecosystem-startups-forum-and-demo-day-at-hong-kong-cyberport-on-december-20-48992","indices":[196,219],"url":"https://t.co/a35D8Npwy0"}],"user_mentions":[],"symbols":[]},"id_str":"1732719636217757843","text":"📢Satoshi Lab is recruiting Bitcoin ecosystem projects to participate in HK Bitcoin Startups Demo Day! \n#btc #Ordinals #BTClayer2 #LightningNetwork #RGB \nRegistration form:https://t.co/RTJtjrBNeW\n\nhttps://t.co/a35D8Npwy0","user":{"id_str":"1364472889282453508","name":"Elaine Yang","profile_image_url_https":"https://pbs.twimg.com/profile_images/1700913366896967680/Em2B_Hzy_normal.jpg","screen_name":"elaineyang73","verified":false,"is_blue_verified":true,"profile_image_shape":"Circle"},"edit_control":{"edit_tweet_ids":["1732719636217757843"],"editable_until_msecs":"1701951128000","is_edit_eligible":true,"edits_remaining":"5"},"conversation_count":0,"news_action_type":"conversation","card":{"card_platform":{"platform":{"audience":{"name":"production"},"device":{"name":"iPhone","version":"13"}}},"name":"summary_large_image","url":"https://t.co/a35D8Npwy0","binding_values":{"photo_image_full_size_large":{"image_value":{"height":419,"width":800,"url":"https://pbs.twimg.com/card_img/1739868623068348416/k1MT5Tmx?format=png&name=800x419"},"type":"IMAGE"},"thumbnail_image":{"image_value":{"height":150,"width":267,"url":"https://pbs.twimg.com/card_img/1739868623068348416/k1MT5Tmx?format=png&name=280x150"},"type":"IMAGE"},"description":{"string_value":"Satoshi Lab will hold the \"Bitcoin Ecosystem Entrepreneurship Forum\" and \"BTC Startups Demo Day\" on December 20th during the \"Hong Kong Web 3.0 Tech Week\"","type":"STRING"},"domain":{"string_value":"www.cointime.ai","type":"STRING"},"thumbnail_image_large":{"image_value":{"height":320,"width":570,"url":"https://pbs.twimg.com/card_img/1739868623068348416/k1MT5Tmx?format=png&name=800x320_1"},"type":"IMAGE"},"summary_photo_image_small":{"image_value":{"height":202,"width":386,"url":"https://pbs.twimg.com/card_img/1739868623068348416/k1MT5Tmx?format=png&name=386x202"},"type":"IMAGE"},"thumbnail_image_original":{"image_value":{"height":541,"width":963,"url":"https://pbs.twimg.com/card_img/1739868623068348416/k1MT5Tmx?format=png&name=orig"},"type":"IMAGE"},"site":{"scribe_key":"publisher_id","type":"USER","user_value":{"id_str":"1590253786282721280","path":[]}},"photo_image_full_size_small":{"image_value":{"height":202,"width":386,"url":"https://pbs.twimg.com/card_img/1739868623068348416/k1MT5Tmx?format=png&name=386x202"},"type":"IMAGE"},"summary_photo_image_large":{"image_value":{"height":419,"width":800,"url":"https://pbs.twimg.com/card_img/1739868623068348416/k1MT5Tmx?format=png&name=800x419"},"type":"IMAGE"},"thumbnail_image_small":{"image_value":{"height":81,"width":144,"url":"https://pbs.twimg.com/card_img/1739868623068348416/k1MT5Tmx?format=png&name=144x144"},"type":"IMAGE"},"creator":{"type":"USER","user_value":{"id_str":"1590253786282721280","path":[]}},"thumbnail_image_x_large":{"image_value":{"height":541,"width":963,"url":"https://pbs.twimg.com/card_img/1739868623068348416/k1MT5Tmx?format=png&name=2048x2048_2_exp"},"type":"IMAGE"},"photo_image_full_size_original":{"image_value":{"height":541,"width":963,"url":"https://pbs.twimg.com/card_img/1739868623068348416/k1MT5Tmx?format=png&name=orig"},"type":"IMAGE"},"vanity_url":{"scribe_key":"vanity_url","string_value":"cointime.ai","type":"STRING"},"photo_image_full_size":{"image_value":{"height":314,"width":600,"url":"https://pbs.twimg.com/card_img/1739868623068348416/k1MT5Tmx?format=png&name=600x314"},"type":"IMAGE"},"thumbnail_image_color":{"image_color_value":{"palette":[{"rgb":{"blue":218,"green":219,"red":230},"percentage":51.95},{"rgb":{"blue":203,"green":148,"red":178},"percentage":17.57},{"rgb":{"blue":0,"green":0,"red":0},"percentage":11.99},{"rgb":{"blue":171,"green":147,"red":242},"percentage":5},{"rgb":{"blue":182,"green":187,"red":156},"percentage":1.57}]},"type":"IMAGE_COLOR"},"title":{"string_value":"Satoshi Lab will hold the Bitcoin Ecosystem Startups Forum and Demo Day at Hong Kong Cyberport on...","type":"STRING"},"summary_photo_image_color":{"image_color_value":{"palette":[{"rgb":{"blue":218,"green":219,"red":230},"percentage":51.95},{"rgb":{"blue":203,"green":148,"red":178},"percentage":17.57},{"rgb":{"blue":0,"green":0,"red":0},"percentage":11.99},{"rgb":{"blue":171,"green":147,"red":242},"percentage":5},{"rgb":{"blue":182,"green":187,"red":156},"percentage":1.57}]},"type":"IMAGE_COLOR"},"summary_photo_image_x_large":{"image_value":{"height":541,"width":963,"url":"https://pbs.twimg.com/card_img/1739868623068348416/k1MT5Tmx?format=png&name=2048x2048_2_exp"},"type":"IMAGE"},"summary_photo_image":{"image_value":{"height":314,"width":600,"url":"https://pbs.twimg.com/card_img/1739868623068348416/k1MT5Tmx?format=png&name=600x314"},"type":"IMAGE"},"photo_image_full_size_color":{"image_color_value":{"palette":[{"rgb":{"blue":218,"green":219,"red":230},"percentage":51.95},{"rgb":{"blue":203,"green":148,"red":178},"percentage":17.57},{"rgb":{"blue":0,"green":0,"red":0},"percentage":11.99},{"rgb":{"blue":171,"green":147,"red":242},"percentage":5},{"rgb":{"blue":182,"green":187,"red":156},"percentage":1.57}]},"type":"IMAGE_COLOR"},"photo_image_full_size_x_large":{"image_value":{"height":541,"width":963,"url":"https://pbs.twimg.com/card_img/1739868623068348416/k1MT5Tmx?format=png&name=2048x2048_2_exp"},"type":"IMAGE"},"card_url":{"scribe_key":"card_url","string_value":"https://t.co/a35D8Npwy0","type":"STRING"},"summary_photo_image_original":{"image_value":{"height":541,"width":963,"url":"https://pbs.twimg.com/card_img/1739868623068348416/k1MT5Tmx?format=png&name=orig"},"type":"IMAGE"}}},"isEdited":false,"isStaleEdit":false}]