[{"__typename":"Tweet","lang":"en","favorite_count":1384,"created_at":"2023-12-28T19:24:25.000Z","display_text_range":[0,275],"entities":{"hashtags":[],"urls":[],"user_mentions":[],"symbols":[{"indices":[6,9],"text":"AI"},{"indices":[23,30],"text":"ANALOS"}]},"id_str":"1740453667860525252","text":"While $AI almost at 0, $ANALOS still above 30M MC\n\nProb MM makes sense\n\nRn we are in some paper loss\n\nBut we are working and supporting the team on Kucoin and other CEXs\n\nGoing to post a huge thread with internal staff to let people know what has been happening inside \n\nSoon","user":{"id_str":"1152137593544462336","name":"Alex Andryunin","profile_image_url_https":"https://pbs.twimg.com/profile_images/1691487078163394565/DSI124pl_normal.jpg","screen_name":"AlexAndryunin","verified":false,"is_blue_verified":true,"profile_image_shape":"Circle"},"edit_control":{"edit_tweet_ids":["1740453667860525252"],"editable_until_msecs":"1703795065000","is_edit_eligible":true,"edits_remaining":"5"},"conversation_count":260,"news_action_type":"conversation","isEdited":false,"isStaleEdit":false},{"__typename":"Tweet","lang":"en","favorite_count":71,"possibly_sensitive":false,"created_at":"2023-11-30T14:04:17.000Z","display_text_range":[0,280],"entities":{"hashtags":[],"urls":[],"user_mentions":[],"symbols":[],"media":[{"display_url":"pic.twitter.com/4SkJ78lasM","expanded_url":"https://twitter.com/crypto_noodles/status/1730226245881774160/photo/1","indices":[281,304],"url":"https://t.co/4SkJ78lasM"}]},"id_str":"1730226245881774160","text":"Months of building, and now Rage v2 is finally in beta!\n\nWe’ve spent about 2 years building / iterating on perp products and all those learning have culminated in v2. I think this can be our mark on the onchain perp space. \n \nIronically in late 2021 (when we got together) nobody… https://t.co/4SkJ78lasM","user":{"id_str":"1310452475640545281","name":"noodles","profile_image_url_https":"https://pbs.twimg.com/profile_images/1310453819101401089/nwRPeM5y_normal.jpg","screen_name":"crypto_noodles","verified":false,"is_blue_verified":true,"profile_image_shape":"Circle"},"edit_control":{"edit_tweet_ids":["1730226245881774160"],"editable_until_msecs":"1701356657000","is_edit_eligible":true,"edits_remaining":"5"},"mediaDetails":[{"display_url":"pic.twitter.com/4SkJ78lasM","expanded_url":"https://twitter.com/crypto_noodles/status/1730226245881774160/photo/1","ext_media_availability":{"status":"Available"},"indices":[281,304],"media_url_https":"https://pbs.twimg.com/media/GAL_hjSW4AEdvNE.png","original_info":{"height":416,"width":420,"focus_rects":[{"x":0,"y":103,"w":420,"h":235},{"x":0,"y":0,"w":416,"h":416},{"x":0,"y":0,"w":365,"h":416},{"x":74,"y":0,"w":208,"h":416},{"x":0,"y":0,"w":420,"h":416}]},"sizes":{"large":{"h":416,"resize":"fit","w":420},"medium":{"h":416,"resize":"fit","w":420},"small":{"h":416,"resize":"fit","w":420},"thumb":{"h":150,"resize":"crop","w":150}},"type":"photo","url":"https://t.co/4SkJ78lasM"}],"photos":[{"backgroundColor":{"red":204,"green":214,"blue":221},"cropCandidates":[{"x":0,"y":103,"w":420,"h":235},{"x":0,"y":0,"w":416,"h":416},{"x":0,"y":0,"w":365,"h":416},{"x":74,"y":0,"w":208,"h":416},{"x":0,"y":0,"w":420,"h":416}],"expandedUrl":"https://twitter.com/crypto_noodles/status/1730226245881774160/photo/1","url":"https://pbs.twimg.com/media/GAL_hjSW4AEdvNE.png","width":420,"height":416}],"conversation_count":24,"news_action_type":"conversation","quoted_tweet":{"lang":"en","reply_count":8,"retweet_count":59,"favorite_count":214,"possibly_sensitive":false,"created_at":"2023-11-30T14:01:49.000Z","display_text_range":[0,272],"entities":{"hashtags":[],"urls":[{"display_url":"discord.gg/3ux53hBQV8","expanded_url":"https://discord.gg/3ux53hBQV8","indices":[248,271],"url":"https://t.co/nKckEYWJzW"}],"user_mentions":[{"id_str":"1363739197018828802","indices":[46,53],"name":"GMX 🫐","screen_name":"GMX_IO"},{"id_str":"898875132864716800","indices":[62,75],"name":"Synthetix ⚔️","screen_name":"synthetix_io"},{"id_str":"1527020295059648513","indices":[83,96],"name":"Hyperliquid","screen_name":"HyperliquidX"},{"id_str":"1573233233122103296","indices":[98,106],"name":"Aevo","screen_name":"aevoxyz"},{"id_str":"909929047626354688","indices":[108,113],"name":"dYdX","screen_name":"dYdX"}],"symbols":[],"media":[{"display_url":"pic.twitter.com/BKlDYrFff8","expanded_url":"https://twitter.com/rage_trade/status/1730225622515937548/photo/1","indices":[272,295],"url":"https://t.co/BKlDYrFff8"}]},"id_str":"1730225622515937548","text":"The Rage v2 Public Beta is live!\n\n• Aggregate @GMX_IO v1/v2 + @synthetix_io\n• Soon @HyperliquidX, @aevoxyz, @dYdX &amp; more\n• 100% rebates on GMX v2\n• Best funding/prices\n• New perp strategies\n• No moving gas b/w chains\n\nJoin Discord for invite 👇\nhttps://t.co/nKckEYWJzW https://t.co/BKlDYrFff8","user":{"id_str":"1328977776523808769","name":"Rage Trade","profile_image_url_https":"https://pbs.twimg.com/profile_images/1518891395636944897/gLh94IR3_normal.png","screen_name":"rage_trade","verified":false,"is_blue_verified":true,"profile_image_shape":"Circle"},"edit_control":{"edit_tweet_ids":["1730225622515937548"],"editable_until_msecs":"1701356509000","is_edit_eligible":true,"edits_remaining":"5"},"mediaDetails":[{"display_url":"pic.twitter.com/BKlDYrFff8","expanded_url":"https://twitter.com/rage_trade/status/1730225622515937548/photo/1","ext_media_availability":{"status":"Available"},"indices":[272,295],"media_url_https":"https://pbs.twimg.com/media/GAL_B_SW8AAjT2V.png","original_info":{"height":500,"width":500,"focus_rects":[{"x":0,"y":0,"w":500,"h":280},{"x":0,"y":0,"w":500,"h":500},{"x":43,"y":0,"w":439,"h":500},{"x":137,"y":0,"w":250,"h":500},{"x":0,"y":0,"w":500,"h":500}]},"sizes":{"large":{"h":500,"resize":"fit","w":500},"medium":{"h":500,"resize":"fit","w":500},"small":{"h":500,"resize":"fit","w":500},"thumb":{"h":150,"resize":"crop","w":150}},"type":"photo","url":"https://t.co/BKlDYrFff8"}],"photos":[{"backgroundColor":{"red":204,"green":214,"blue":221},"cropCandidates":[{"x":0,"y":0,"w":500,"h":280},{"x":0,"y":0,"w":500,"h":500},{"x":43,"y":0,"w":439,"h":500},{"x":137,"y":0,"w":250,"h":500},{"x":0,"y":0,"w":500,"h":500}],"expandedUrl":"https://twitter.com/rage_trade/status/1730225622515937548/photo/1","url":"https://pbs.twimg.com/media/GAL_B_SW8AAjT2V.png","width":500,"height":500}],"isEdited":false,"isStaleEdit":false},"isEdited":false,"isStaleEdit":false,"note_tweet":{"id":"Tm90ZVR3ZWV0UmVzdWx0czoxNzMwMjI2MjQ1NTg4MTQwMDMy"}},{"__typename":"Tweet","lang":"en","favorite_count":37849,"possibly_sensitive":false,"created_at":"2023-12-29T16:46:16.000Z","display_text_range":[0,280],"entities":{"hashtags":[],"urls":[],"user_mentions":[],"symbols":[],"media":[{"display_url":"pic.twitter.com/yuiSzxh2jo","expanded_url":"https://twitter.com/Nico_ETH/status/1740776258881876261/photo/1","indices":[279,302],"url":"https://t.co/yuiSzxh2jo"}]},"id_str":"1740776258881876261","text":"The most undervalued project in the whole space right now is about to make big moves.\n\nSmart money is already accumulating, and a big campaign is starting now by the time of writing!\n\nDon’t miss this chance, and keep on reading; it could literally change your lives. 🧵👇\n\nFirst,… https://t.co/yuiSzxh2jo","user":{"id_str":"1454431885124378631","name":"NftGen","profile_image_url_https":"https://pbs.twimg.com/profile_images/1610353038069202945/-CmxQRc6_normal.jpg","screen_name":"Nico_ETH","verified":false,"is_blue_verified":true,"profile_image_shape":"Circle"},"edit_control":{"edit_tweet_ids":["1740776258881876261"],"editable_until_msecs":"1703871976000","is_edit_eligible":true,"edits_remaining":"5"},"mediaDetails":[{"display_url":"pic.twitter.com/yuiSzxh2jo","expanded_url":"https://twitter.com/Nico_ETH/status/1740776258881876261/photo/1","ext_media_availability":{"status":"Available"},"indices":[279,302],"media_url_https":"https://pbs.twimg.com/media/GChIKfhWkAAeYgr.jpg","original_info":{"height":1024,"width":1024,"focus_rects":[{"x":0,"y":451,"w":1024,"h":573},{"x":0,"y":0,"w":1024,"h":1024},{"x":37,"y":0,"w":898,"h":1024},{"x":230,"y":0,"w":512,"h":1024},{"x":0,"y":0,"w":1024,"h":1024}]},"sizes":{"large":{"h":1024,"resize":"fit","w":1024},"medium":{"h":1024,"resize":"fit","w":1024},"small":{"h":680,"resize":"fit","w":680},"thumb":{"h":150,"resize":"crop","w":150}},"type":"photo","url":"https://t.co/yuiSzxh2jo"},{"display_url":"pic.twitter.com/yuiSzxh2jo","expanded_url":"https://twitter.com/Nico_ETH/status/1740776258881876261/photo/1","ext_media_availability":{"status":"Available"},"indices":[279,302],"media_url_https":"https://pbs.twimg.com/media/GChIr1DW0AAL6Eu.jpg","original_info":{"height":1165,"width":2048,"focus_rects":[{"x":0,"y":0,"w":2048,"h":1147},{"x":390,"y":0,"w":1165,"h":1165},{"x":461,"y":0,"w":1022,"h":1165},{"x":681,"y":0,"w":583,"h":1165},{"x":0,"y":0,"w":2048,"h":1165}]},"sizes":{"large":{"h":1165,"resize":"fit","w":2048},"medium":{"h":683,"resize":"fit","w":1200},"small":{"h":387,"resize":"fit","w":680},"thumb":{"h":150,"resize":"crop","w":150}},"type":"photo","url":"https://t.co/yuiSzxh2jo"},{"display_url":"pic.twitter.com/yuiSzxh2jo","expanded_url":"https://twitter.com/Nico_ETH/status/1740776258881876261/photo/1","ext_media_availability":{"status":"Available"},"indices":[279,302],"media_url_https":"https://pbs.twimg.com/media/GChI8fmXYAAw0aX.jpg","original_info":{"height":1080,"width":1080,"focus_rects":[{"x":0,"y":0,"w":1080,"h":605},{"x":0,"y":0,"w":1080,"h":1080},{"x":94,"y":0,"w":947,"h":1080},{"x":297,"y":0,"w":540,"h":1080},{"x":0,"y":0,"w":1080,"h":1080}]},"sizes":{"large":{"h":1080,"resize":"fit","w":1080},"medium":{"h":1080,"resize":"fit","w":1080},"small":{"h":680,"resize":"fit","w":680},"thumb":{"h":150,"resize":"crop","w":150}},"type":"photo","url":"https://t.co/yuiSzxh2jo"},{"display_url":"pic.twitter.com/yuiSzxh2jo","expanded_url":"https://twitter.com/Nico_ETH/status/1740776258881876261/photo/1","ext_media_availability":{"status":"Available"},"indices":[279,302],"media_url_https":"https://pbs.twimg.com/media/GChJgZaXEAAKzF2.jpg","original_info":{"height":500,"width":1500,"focus_rects":[{"x":0,"y":0,"w":893,"h":500},{"x":161,"y":0,"w":500,"h":500},{"x":192,"y":0,"w":439,"h":500},{"x":286,"y":0,"w":250,"h":500},{"x":0,"y":0,"w":1500,"h":500}]},"sizes":{"large":{"h":500,"resize":"fit","w":1500},"medium":{"h":400,"resize":"fit","w":1200},"small":{"h":227,"resize":"fit","w":680},"thumb":{"h":150,"resize":"crop","w":150}},"type":"photo","url":"https://t.co/yuiSzxh2jo"}],"photos":[{"backgroundColor":{"red":204,"green":214,"blue":221},"cropCandidates":[{"x":0,"y":451,"w":1024,"h":573},{"x":0,"y":0,"w":1024,"h":1024},{"x":37,"y":0,"w":898,"h":1024},{"x":230,"y":0,"w":512,"h":1024},{"x":0,"y":0,"w":1024,"h":1024}],"expandedUrl":"https://twitter.com/Nico_ETH/status/1740776258881876261/photo/1","url":"https://pbs.twimg.com/media/GChIKfhWkAAeYgr.jpg","width":1024,"height":1024},{"backgroundColor":{"red":204,"green":214,"blue":221},"cropCandidates":[{"x":0,"y":0,"w":2048,"h":1147},{"x":390,"y":0,"w":1165,"h":1165},{"x":461,"y":0,"w":1022,"h":1165},{"x":681,"y":0,"w":583,"h":1165},{"x":0,"y":0,"w":2048,"h":1165}],"expandedUrl":"https://twitter.com/Nico_ETH/status/1740776258881876261/photo/1","url":"https://pbs.twimg.com/media/GChIr1DW0AAL6Eu.jpg","width":2048,"height":1165},{"backgroundColor":{"red":204,"green":214,"blue":221},"cropCandidates":[{"x":0,"y":0,"w":1080,"h":605},{"x":0,"y":0,"w":1080,"h":1080},{"x":94,"y":0,"w":947,"h":1080},{"x":297,"y":0,"w":540,"h":1080},{"x":0,"y":0,"w":1080,"h":1080}],"expandedUrl":"https://twitter.com/Nico_ETH/status/1740776258881876261/photo/1","url":"https://pbs.twimg.com/media/GChI8fmXYAAw0aX.jpg","width":1080,"height":1080},{"backgroundColor":{"red":204,"green":214,"blue":221},"cropCandidates":[{"x":0,"y":0,"w":893,"h":500},{"x":161,"y":0,"w":500,"h":500},{"x":192,"y":0,"w":439,"h":500},{"x":286,"y":0,"w":250,"h":500},{"x":0,"y":0,"w":1500,"h":500}],"expandedUrl":"https://twitter.com/Nico_ETH/status/1740776258881876261/photo/1","url":"https://pbs.twimg.com/media/GChJgZaXEAAKzF2.jpg","width":1500,"height":500}],"conversation_count":3543,"news_action_type":"conversation","isEdited":false,"isStaleEdit":false,"note_tweet":{"id":"Tm90ZVR3ZWV0UmVzdWx0czoxNzQwNzc2MjU4MzgyODAyOTQ0"}}]